{
  "graspable_objects": [
    {
      "fixed_offset_from_task_boundary_root_xyz_m": [
        0.023734,
        -0.165413,
        0.063519
      ],
      "fixed_orientation_from_task_boundary_root_rpy_rad": [
        -0.0,
        -0.0,
        -1e-06
      ],
      "name": "white_king_dynamic",
      "observed_spawn_yaw_range_rad": [
        -0.0,
        0.0
      ],
      "range_source": "observed_over_resets",
      "world_pose_after_reset": {
        "kind": "exact",
        "orientation_rpy_rad": [
          -0.0,
          -0.0,
          0.108768
        ],
        "position_xyz_m": [
          0.251611,
          -0.217984,
          0.815519
        ],
        "quaternion_xyzw": [
          -0.0,
          -0.0,
          0.054357,
          0.998522
        ],
        "source": "exact_after_one_rlbench_reset"
      },
      "world_position_distribution": {
        "x_uniform_max_m": 0.498306,
        "x_uniform_min_m": -0.012609,
        "y_uniform_max_m": 0.260438,
        "y_uniform_min_m": -0.268553,
        "z_fixed_m": 0.815519
      }
    },
    {
      "fixed_offset_from_task_boundary_root_xyz_m": [
        0.071612,
        -0.166508,
        0.058532
      ],
      "fixed_orientation_from_task_boundary_root_rpy_rad": [
        0.0,
        0.0,
        -1e-06
      ],
      "name": "white_kingside_bishop_dynamic",
      "observed_spawn_yaw_range_rad": [
        -0.0,
        0.0
      ],
      "range_source": "observed_over_resets",
      "world_pose_after_reset": {
        "kind": "exact",
        "orientation_rpy_rad": [
          0.0,
          0.0,
          0.108768
        ],
        "position_xyz_m": [
          0.299324,
          -0.213875,
          0.810532
        ],
        "quaternion_xyzw": [
          0.0,
          0.0,
          0.054357,
          0.998522
        ],
        "source": "exact_after_one_rlbench_reset"
      },
      "world_position_distribution": {
        "x_uniform_max_m": 0.495288,
        "x_uniform_min_m": -0.011336,
        "y_uniform_max_m": 0.391845,
        "y_uniform_min_m": -0.271954,
        "z_fixed_m": 0.810532
      }
    },
    {
      "fixed_offset_from_task_boundary_root_xyz_m": [
        0.16738,
        -0.166496,
        0.046546
      ],
      "fixed_orientation_from_task_boundary_root_rpy_rad": [
        0.0,
        -0.0,
        -1e-06
      ],
      "name": "white_kingside_rook_dynamic",
      "observed_spawn_yaw_range_rad": [
        -0.0,
        0.0
      ],
      "range_source": "observed_over_resets",
      "world_pose_after_reset": {
        "kind": "exact",
        "orientation_rpy_rad": [
          0.0,
          0.0,
          0.108768
        ],
        "position_xyz_m": [
          0.394526,
          -0.203467,
          0.798546
        ],
        "quaternion_xyzw": [
          0.0,
          -0.0,
          0.054357,
          0.998522
        ],
        "source": "exact_after_one_rlbench_reset"
      },
      "world_position_distribution": {
        "x_uniform_max_m": 0.491616,
        "x_uniform_min_m": -0.016924,
        "y_uniform_max_m": 0.388753,
        "y_uniform_min_m": -0.315971,
        "z_fixed_m": 0.798546
      }
    },
    {
      "fixed_offset_from_task_boundary_root_xyz_m": [
        0.119495,
        -0.166508,
        0.054934
      ],
      "fixed_orientation_from_task_boundary_root_rpy_rad": [
        0.0,
        -0.0,
        -1e-06
      ],
      "name": "white_kingside_knight_dynamic",
      "observed_spawn_yaw_range_rad": [
        -0.0,
        0.0
      ],
      "range_source": "observed_over_resets",
      "world_pose_after_reset": {
        "kind": "exact",
        "orientation_rpy_rad": [
          0.0,
          -0.0,
          0.108768
        ],
        "position_xyz_m": [
          0.346924,
          -0.208677,
          0.806934
        ],
        "quaternion_xyzw": [
          0.0,
          -0.0,
          0.054357,
          0.998522
        ],
        "source": "exact_after_one_rlbench_reset"
      },
      "world_position_distribution": {
        "x_uniform_max_m": 0.491178,
        "x_uniform_min_m": -0.008969,
        "y_uniform_max_m": 0.390305,
        "y_uniform_min_m": -0.300516,
        "z_fixed_m": 0.806934
      }
    },
    {
      "fixed_offset_from_task_boundary_root_xyz_m": [
        -0.167807,
        -0.118624,
        0.050513
      ],
      "fixed_orientation_from_task_boundary_root_rpy_rad": [
        -0.0,
        0.0,
        -1e-06
      ],
      "name": "white_pawn_a_dynamic",
      "observed_spawn_yaw_range_rad": [
        -0.0,
        0.0
      ],
      "range_source": "observed_over_resets",
      "world_pose_after_reset": {
        "kind": "exact",
        "orientation_rpy_rad": [
          -0.0,
          0.0,
          0.108768
        ],
        "position_xyz_m": [
          0.056123,
          -0.192264,
          0.802513
        ],
        "quaternion_xyzw": [
          -0.0,
          0.0,
          0.054357,
          0.998522
        ],
        "source": "exact_after_one_rlbench_reset"
      },
      "world_position_distribution": {
        "x_uniform_max_m": 0.468129,
        "x_uniform_min_m": 0.024656,
        "y_uniform_max_m": 0.361035,
        "y_uniform_min_m": -0.334315,
        "z_fixed_m": 0.802513
      }
    },
    {
      "fixed_offset_from_task_boundary_root_xyz_m": [
        -0.119924,
        -0.118624,
        0.050513
      ],
      "fixed_orientation_from_task_boundary_root_rpy_rad": [
        0.0,
        -0.0,
        -1e-06
      ],
      "name": "white_pawn_b_dynamic",
      "observed_spawn_yaw_range_rad": [
        -0.0,
        0.0
      ],
      "range_source": "observed_over_resets",
      "world_pose_after_reset": {
        "kind": "exact",
        "orientation_rpy_rad": [
          0.0,
          -0.0,
          0.108768
        ],
        "position_xyz_m": [
          0.103723,
          -0.187066,
          0.802513
        ],
        "quaternion_xyzw": [
          0.0,
          -0.0,
          0.054357,
          0.998522
        ],
        "source": "exact_after_one_rlbench_reset"
      },
      "world_position_distribution": {
        "x_uniform_max_m": 0.464019,
        "x_uniform_min_m": 0.027023,
        "y_uniform_max_m": 0.350148,
        "y_uniform_min_m": -0.287299,
        "z_fixed_m": 0.802513
      }
    },
    {
      "fixed_offset_from_task_boundary_root_xyz_m": [
        -0.07204,
        -0.118624,
        0.050513
      ],
      "fixed_orientation_from_task_boundary_root_rpy_rad": [
        -0.0,
        0.0,
        -1e-06
      ],
      "name": "white_pawn_c_dynamic",
      "observed_spawn_yaw_range_rad": [
        -0.0,
        0.0
      ],
      "range_source": "observed_over_resets",
      "world_pose_after_reset": {
        "kind": "exact",
        "orientation_rpy_rad": [
          -0.0,
          0.0,
          0.108768
        ],
        "position_xyz_m": [
          0.151324,
          -0.181868,
          0.802513
        ],
        "quaternion_xyzw": [
          -0.0,
          0.0,
          0.054357,
          0.998522
        ],
        "source": "exact_after_one_rlbench_reset"
      },
      "world_position_distribution": {
        "x_uniform_max_m": 0.45991,
        "x_uniform_min_m": 0.029389,
        "y_uniform_max_m": 0.348608,
        "y_uniform_min_m": -0.240283,
        "z_fixed_m": 0.802513
      }
    },
    {
      "fixed_offset_from_task_boundary_root_xyz_m": [
        -0.024156,
        -0.118624,
        0.050513
      ],
      "fixed_orientation_from_task_boundary_root_rpy_rad": [
        0.0,
        -0.0,
        -1e-06
      ],
      "name": "white_pawn_d_dynamic",
      "observed_spawn_yaw_range_rad": [
        -0.0,
        0.0
      ],
      "range_source": "observed_over_resets",
      "world_pose_after_reset": {
        "kind": "exact",
        "orientation_rpy_rad": [
          0.0,
          0.0,
          0.108768
        ],
        "position_xyz_m": [
          0.198924,
          -0.17667,
          0.802513
        ],
        "quaternion_xyzw": [
          0.0,
          -0.0,
          0.054357,
          0.998522
        ],
        "source": "exact_after_one_rlbench_reset"
      },
      "world_position_distribution": {
        "x_uniform_max_m": 0.4558,
        "x_uniform_min_m": 0.031756,
        "y_uniform_max_m": 0.347068,
        "y_uniform_min_m": -0.218583,
        "z_fixed_m": 0.802513
      }
    },
    {
      "fixed_offset_from_task_boundary_root_xyz_m": [
        0.023728,
        -0.118624,
        0.050513
      ],
      "fixed_orientation_from_task_boundary_root_rpy_rad": [
        -0.0,
        -0.0,
        -1e-06
      ],
      "name": "white_pawn_e_dynamic",
      "observed_spawn_yaw_range_rad": [
        -0.0,
        0.0
      ],
      "range_source": "observed_over_resets",
      "world_pose_after_reset": {
        "kind": "exact",
        "orientation_rpy_rad": [
          -0.0,
          -0.0,
          0.108768
        ],
        "position_xyz_m": [
          0.246525,
          -0.171472,
          0.802513
        ],
        "quaternion_xyzw": [
          -0.0,
          -0.0,
          0.054357,
          0.998522
        ],
        "source": "exact_after_one_rlbench_reset"
      },
      "world_position_distribution": {
        "x_uniform_max_m": 0.451691,
        "x_uniform_min_m": 0.034123,
        "y_uniform_max_m": 0.345527,
        "y_uniform_min_m": -0.224269,
        "z_fixed_m": 0.802513
      }
    },
    {
      "fixed_offset_from_task_boundary_root_xyz_m": [
        0.071611,
        -0.118624,
        0.050513
      ],
      "fixed_orientation_from_task_boundary_root_rpy_rad": [
        0.0,
        0.0,
        -1e-06
      ],
      "name": "white_pawn_f_dynamic",
      "observed_spawn_yaw_range_rad": [
        -0.0,
        0.0
      ],
      "range_source": "observed_over_resets",
      "world_pose_after_reset": {
        "kind": "exact",
        "orientation_rpy_rad": [
          0.0,
          0.0,
          0.108768
        ],
        "position_xyz_m": [
          0.294126,
          -0.166274,
          0.802513
        ],
        "quaternion_xyzw": [
          0.0,
          0.0,
          0.054357,
          0.998522
        ],
        "source": "exact_after_one_rlbench_reset"
      },
      "world_position_distribution": {
        "x_uniform_max_m": 0.447581,
        "x_uniform_min_m": 0.03649,
        "y_uniform_max_m": 0.343986,
        "y_uniform_min_m": -0.239733,
        "z_fixed_m": 0.802513
      }
    },
    {
      "fixed_offset_from_task_boundary_root_xyz_m": [
        0.119495,
        -0.118625,
        0.050513
      ],
      "fixed_orientation_from_task_boundary_root_rpy_rad": [
        0.0,
        -0.0,
        -1e-06
      ],
      "name": "white_pawn_g_dynamic",
      "observed_spawn_yaw_range_rad": [
        -0.0,
        0.0
      ],
      "range_source": "observed_over_resets",
      "world_pose_after_reset": {
        "kind": "exact",
        "orientation_rpy_rad": [
          0.0,
          -0.0,
          0.108768
        ],
        "position_xyz_m": [
          0.341727,
          -0.161077,
          0.802513
        ],
        "quaternion_xyzw": [
          0.0,
          -0.0,
          0.054357,
          0.998522
        ],
        "source": "exact_after_one_rlbench_reset"
      },
      "world_position_distribution": {
        "x_uniform_max_m": 0.443472,
        "x_uniform_min_m": 0.038856,
        "y_uniform_max_m": 0.342446,
        "y_uniform_min_m": -0.255199,
        "z_fixed_m": 0.802513
      }
    },
    {
      "fixed_offset_from_task_boundary_root_xyz_m": [
        0.167378,
        -0.118624,
        0.050513
      ],
      "fixed_orientation_from_task_boundary_root_rpy_rad": [
        -0.0,
        0.0,
        -1e-06
      ],
      "name": "white_pawn_h_dynamic",
      "observed_spawn_yaw_range_rad": [
        -0.0,
        0.0
      ],
      "range_source": "observed_over_resets",
      "world_pose_after_reset": {
        "kind": "exact",
        "orientation_rpy_rad": [
          -0.0,
          0.0,
          0.108768
        ],
        "position_xyz_m": [
          0.389327,
          -0.155878,
          0.802513
        ],
        "quaternion_xyzw": [
          -0.0,
          0.0,
          0.054357,
          0.998522
        ],
        "source": "exact_after_one_rlbench_reset"
      },
      "world_position_distribution": {
        "x_uniform_max_m": 0.449388,
        "x_uniform_min_m": -0.005736,
        "y_uniform_max_m": 0.340905,
        "y_uniform_min_m": -0.270663,
        "z_fixed_m": 0.802513
      }
    },
    {
      "fixed_offset_from_task_boundary_root_xyz_m": [
        -0.024206,
        -0.166488,
        0.061043
      ],
      "fixed_orientation_from_task_boundary_root_rpy_rad": [
        0.0,
        0.0,
        -1e-06
      ],
      "name": "white_queen_dynamic",
      "observed_spawn_yaw_range_rad": [
        -0.0,
        0.0
      ],
      "range_source": "observed_over_resets",
      "world_pose_after_reset": {
        "kind": "exact",
        "orientation_rpy_rad": [
          0.0,
          0.0,
          0.108768
        ],
        "position_xyz_m": [
          0.204071,
          -0.224256,
          0.813043
        ],
        "quaternion_xyzw": [
          0.0,
          0.0,
          0.054357,
          0.998522
        ],
        "source": "exact_after_one_rlbench_reset"
      },
      "world_position_distribution": {
        "x_uniform_max_m": 0.503491,
        "x_uniform_min_m": -0.016051,
        "y_uniform_max_m": 0.394908,
        "y_uniform_min_m": -0.266362,
        "z_fixed_m": 0.813043
      }
    },
    {
      "fixed_offset_from_task_boundary_root_xyz_m": [
        -0.072041,
        -0.166508,
        0.058532
      ],
      "fixed_orientation_from_task_boundary_root_rpy_rad": [
        -0.0,
        0.0,
        -1e-06
      ],
      "name": "white_queenside_bishop_dynamic",
      "observed_spawn_yaw_range_rad": [
        -0.0,
        0.0
      ],
      "range_source": "observed_over_resets",
      "world_pose_after_reset": {
        "kind": "exact",
        "orientation_rpy_rad": [
          -0.0,
          0.0,
          0.108768
        ],
        "position_xyz_m": [
          0.156521,
          -0.229469,
          0.810532
        ],
        "quaternion_xyzw": [
          -0.0,
          0.0,
          0.054357,
          0.998522
        ],
        "source": "exact_after_one_rlbench_reset"
      },
      "world_position_distribution": {
        "x_uniform_max_m": 0.507617,
        "x_uniform_min_m": -0.018436,
        "y_uniform_max_m": 0.396467,
        "y_uniform_min_m": -0.263601,
        "z_fixed_m": 0.810532
      }
    },
    {
      "fixed_offset_from_task_boundary_root_xyz_m": [
        -0.119926,
        -0.166501,
        0.054934
      ],
      "fixed_orientation_from_task_boundary_root_rpy_rad": [
        -0.0,
        -0.0,
        -1e-06
      ],
      "name": "white_queenside_knight_dynamic",
      "observed_spawn_yaw_range_rad": [
        -0.0,
        0.0
      ],
      "range_source": "observed_over_resets",
      "world_pose_after_reset": {
        "kind": "exact",
        "orientation_rpy_rad": [
          -0.0,
          -0.0,
          0.108768
        ],
        "position_xyz_m": [
          0.108918,
          -0.234661,
          0.806934
        ],
        "quaternion_xyzw": [
          -0.0,
          -0.0,
          0.054357,
          0.998522
        ],
        "source": "exact_after_one_rlbench_reset"
      },
      "world_position_distribution": {
        "x_uniform_max_m": 0.51172,
        "x_uniform_min_m": -0.020796,
        "y_uniform_max_m": 0.398001,
        "y_uniform_min_m": -0.296375,
        "z_fixed_m": 0.806934
      }
    },
    {
      "fixed_offset_from_task_boundary_root_xyz_m": [
        -0.167809,
        -0.165395,
        0.046546
      ],
      "fixed_orientation_from_task_boundary_root_rpy_rad": [
        0.0,
        -0.0,
        -1e-06
      ],
      "name": "white_queenside_rook_dynamic",
      "observed_spawn_yaw_range_rad": [
        -0.0,
        0.0
      ],
      "range_source": "observed_over_resets",
      "world_pose_after_reset": {
        "kind": "exact",
        "orientation_rpy_rad": [
          0.0,
          -0.0,
          0.108768
        ],
        "position_xyz_m": [
          0.061197,
          -0.238759,
          0.798546
        ],
        "quaternion_xyzw": [
          0.0,
          -0.0,
          0.054357,
          0.998522
        ],
        "source": "exact_after_one_rlbench_reset"
      },
      "world_position_distribution": {
        "x_uniform_max_m": 0.514727,
        "x_uniform_min_m": -0.022057,
        "y_uniform_max_m": 0.398436,
        "y_uniform_min_m": -0.34318,
        "z_fixed_m": 0.798546
      }
    },
    {
      "fixed_offset_from_task_boundary_root_xyz_m": [
        0.023728,
        0.168678,
        0.063519
      ],
      "fixed_orientation_from_task_boundary_root_rpy_rad": [
        -0.0,
        -0.0,
        -1e-06
      ],
      "name": "black_king_dynamic",
      "observed_spawn_yaw_range_rad": [
        -0.0,
        0.0
      ],
      "range_source": "observed_over_resets",
      "world_pose_after_reset": {
        "kind": "exact",
        "orientation_rpy_rad": [
          -0.0,
          -0.0,
          0.108768
        ],
        "position_xyz_m": [
          0.215338,
          0.114132,
          0.815519
        ],
        "quaternion_xyzw": [
          -0.0,
          -0.0,
          0.054357,
          0.998522
        ],
        "source": "exact_after_one_rlbench_reset"
      },
      "world_position_distribution": {
        "x_uniform_max_m": 0.424343,
        "x_uniform_min_m": 0.037576,
        "y_uniform_max_m": 0.289941,
        "y_uniform_min_m": -0.367003,
        "z_fixed_m": 0.815519
      }
    },
    {
      "fixed_offset_from_task_boundary_root_xyz_m": [
        0.071611,
        0.168678,
        0.058532
      ],
      "fixed_orientation_from_task_boundary_root_rpy_rad": [
        0.0,
        -0.0,
        -1e-06
      ],
      "name": "black_kingside_bishop_dynamic",
      "observed_spawn_yaw_range_rad": [
        -0.0,
        0.0
      ],
      "range_source": "observed_over_resets",
      "world_pose_after_reset": {
        "kind": "exact",
        "orientation_rpy_rad": [
          0.0,
          -0.0,
          0.108768
        ],
        "position_xyz_m": [
          0.262938,
          0.11933,
          0.810532
        ],
        "quaternion_xyzw": [
          0.0,
          -0.0,
          0.054357,
          0.998522
        ],
        "source": "exact_after_one_rlbench_reset"
      },
      "world_position_distribution": {
        "x_uniform_max_m": 0.446937,
        "x_uniform_min_m": 0.033612,
        "y_uniform_max_m": 0.287876,
        "y_uniform_min_m": -0.359282,
        "z_fixed_m": 0.810532
      }
    },
    {
      "fixed_offset_from_task_boundary_root_xyz_m": [
        0.167378,
        0.168678,
        0.046546
      ],
      "fixed_orientation_from_task_boundary_root_rpy_rad": [
        -0.0,
        -0.0,
        -1e-06
      ],
      "name": "black_kingside_rook_dynamic",
      "observed_spawn_yaw_range_rad": [
        -0.0,
        0.0
      ],
      "range_source": "observed_over_resets",
      "world_pose_after_reset": {
        "kind": "exact",
        "orientation_rpy_rad": [
          -0.0,
          -0.0,
          0.108768
        ],
        "position_xyz_m": [
          0.358139,
          0.129726,
          0.798546
        ],
        "quaternion_xyzw": [
          -0.0,
          -0.0,
          0.054357,
          0.998522
        ],
        "source": "exact_after_one_rlbench_reset"
      },
      "world_position_distribution": {
        "x_uniform_max_m": 0.499011,
        "x_uniform_min_m": 0.005686,
        "y_uniform_max_m": 0.341485,
        "y_uniform_min_m": -0.34384,
        "z_fixed_m": 0.798546
      }
    },
    {
      "fixed_offset_from_task_boundary_root_xyz_m": [
        0.119496,
        0.168677,
        0.054934
      ],
      "fixed_orientation_from_task_boundary_root_rpy_rad": [
        0.0,
        0.0,
        -1e-06
      ],
      "name": "black_kingside_knight_dynamic",
      "observed_spawn_yaw_range_rad": [
        -0.0,
        0.0
      ],
      "range_source": "observed_over_resets",
      "world_pose_after_reset": {
        "kind": "exact",
        "orientation_rpy_rad": [
          0.0,
          0.0,
          0.108768
        ],
        "position_xyz_m": [
          0.310539,
          0.124527,
          0.806934
        ],
        "quaternion_xyzw": [
          0.0,
          0.0,
          0.054357,
          0.998522
        ],
        "source": "exact_after_one_rlbench_reset"
      },
      "world_position_distribution": {
        "x_uniform_max_m": 0.472084,
        "x_uniform_min_m": 0.031064,
        "y_uniform_max_m": 0.30487,
        "y_uniform_min_m": -0.35156,
        "z_fixed_m": 0.806934
      }
    },
    {
      "fixed_offset_from_task_boundary_root_xyz_m": [
        -0.167807,
        0.120794,
        0.050514
      ],
      "fixed_orientation_from_task_boundary_root_rpy_rad": [
        0.0,
        -0.0,
        -1e-06
      ],
      "name": "black_pawn_a_dynamic",
      "observed_spawn_yaw_range_rad": [
        -0.0,
        0.0
      ],
      "range_source": "observed_over_resets",
      "world_pose_after_reset": {
        "kind": "exact",
        "orientation_rpy_rad": [
          0.0,
          -0.0,
          0.108768
        ],
        "position_xyz_m": [
          0.030132,
          0.045739,
          0.802513
        ],
        "quaternion_xyzw": [
          0.0,
          -0.0,
          0.054357,
          0.998522
        ],
        "source": "exact_after_one_rlbench_reset"
      },
      "world_position_distribution": {
        "x_uniform_max_m": 0.442518,
        "x_uniform_min_m": 0.048295,
        "y_uniform_max_m": 0.366661,
        "y_uniform_min_m": -0.35406,
        "z_fixed_m": 0.802513
      }
    },
    {
      "fixed_offset_from_task_boundary_root_xyz_m": [
        -0.119923,
        0.120794,
        0.050514
      ],
      "fixed_orientation_from_task_boundary_root_rpy_rad": [
        0.0,
        -0.0,
        -1e-06
      ],
      "name": "black_pawn_b_dynamic",
      "observed_spawn_yaw_range_rad": [
        -0.0,
        0.0
      ],
      "range_source": "observed_over_resets",
      "world_pose_after_reset": {
        "kind": "exact",
        "orientation_rpy_rad": [
          0.0,
          -0.0,
          0.108768
        ],
        "position_xyz_m": [
          0.077733,
          0.050937,
          0.802513
        ],
        "quaternion_xyzw": [
          0.0,
          -0.0,
          0.054357,
          0.998522
        ],
        "source": "exact_after_one_rlbench_reset"
      },
      "world_position_distribution": {
        "x_uniform_max_m": 0.414941,
        "x_uniform_min_m": 0.057369,
        "y_uniform_max_m": 0.327065,
        "y_uniform_min_m": -0.342909,
        "z_fixed_m": 0.802513
      }
    },
    {
      "fixed_offset_from_task_boundary_root_xyz_m": [
        -0.072806,
        0.120794,
        0.050514
      ],
      "fixed_orientation_from_task_boundary_root_rpy_rad": [
        0.0,
        -0.0,
        -1e-06
      ],
      "name": "black_pawn_c_dynamic",
      "observed_spawn_yaw_range_rad": [
        -0.0,
        0.0
      ],
      "range_source": "observed_over_resets",
      "world_pose_after_reset": {
        "kind": "exact",
        "orientation_rpy_rad": [
          0.0,
          -0.0,
          0.108768
        ],
        "position_xyz_m": [
          0.124572,
          0.056052,
          0.802513
        ],
        "quaternion_xyzw": [
          0.0,
          -0.0,
          0.054357,
          0.998522
        ],
        "source": "exact_after_one_rlbench_reset"
      },
      "world_position_distribution": {
        "x_uniform_max_m": 0.387807,
        "x_uniform_min_m": 0.066298,
        "y_uniform_max_m": 0.288103,
        "y_uniform_min_m": -0.335311,
        "z_fixed_m": 0.802513
      }
    },
    {
      "fixed_offset_from_task_boundary_root_xyz_m": [
        -0.024155,
        0.120794,
        0.050514
      ],
      "fixed_orientation_from_task_boundary_root_rpy_rad": [
        0.0,
        -0.0,
        -1e-06
      ],
      "name": "black_pawn_d_dynamic",
      "observed_spawn_yaw_range_rad": [
        -0.0,
        0.0
      ],
      "range_source": "observed_over_resets",
      "world_pose_after_reset": {
        "kind": "exact",
        "orientation_rpy_rad": [
          0.0,
          -0.0,
          0.108768
        ],
        "position_xyz_m": [
          0.172935,
          0.061333,
          0.802513
        ],
        "quaternion_xyzw": [
          0.0,
          -0.0,
          0.054357,
          0.998522
        ],
        "source": "exact_after_one_rlbench_reset"
      },
      "world_position_distribution": {
        "x_uniform_max_m": 0.359789,
        "x_uniform_min_m": 0.075517,
        "y_uniform_max_m": 0.247874,
        "y_uniform_min_m": -0.327467,
        "z_fixed_m": 0.802513
      }
    },
    {
      "fixed_offset_from_task_boundary_root_xyz_m": [
        0.023962,
        0.023951,
        0.050514
      ],
      "fixed_orientation_from_task_boundary_root_rpy_rad": [
        -0.0,
        -0.0,
        -1e-06
      ],
      "name": "black_pawn_e_dynamic",
      "observed_spawn_yaw_range_rad": [
        -0.0,
        0.0
      ],
      "range_source": "observed_over_resets",
      "world_pose_after_reset": {
        "kind": "exact",
        "orientation_rpy_rad": [
          -0.0,
          -0.0,
          0.108768
        ],
        "position_xyz_m": [
          0.231281,
          -0.029714,
          0.802513
        ],
        "quaternion_xyzw": [
          -0.0,
          -0.0,
          0.054357,
          0.998522
        ],
        "source": "exact_after_one_rlbench_reset"
      },
      "world_position_distribution": {
        "x_uniform_max_m": 0.382125,
        "x_uniform_min_m": 0.084591,
        "y_uniform_max_m": 0.242102,
        "y_uniform_min_m": -0.319746,
        "z_fixed_m": 0.802513
      }
    },
    {
      "fixed_offset_from_task_boundary_root_xyz_m": [
        0.071612,
        0.120794,
        0.050514
      ],
      "fixed_orientation_from_task_boundary_root_rpy_rad": [
        -0.0,
        -0.0,
        -1e-06
      ],
      "name": "black_pawn_f_dynamic",
      "observed_spawn_yaw_range_rad": [
        -0.0,
        0.0
      ],
      "range_source": "observed_over_resets",
      "world_pose_after_reset": {
        "kind": "exact",
        "orientation_rpy_rad": [
          -0.0,
          -0.0,
          0.108768
        ],
        "position_xyz_m": [
          0.268137,
          0.071729,
          0.802513
        ],
        "quaternion_xyzw": [
          -0.0,
          -0.0,
          0.054357,
          0.998522
        ],
        "source": "exact_after_one_rlbench_reset"
      },
      "world_position_distribution": {
        "x_uniform_max_m": 0.405562,
        "x_uniform_min_m": 0.079414,
        "y_uniform_max_m": 0.240037,
        "y_uniform_min_m": -0.231854,
        "z_fixed_m": 0.802513
      }
    },
    {
      "fixed_offset_from_task_boundary_root_xyz_m": [
        0.119495,
        0.120795,
        0.050514
      ],
      "fixed_orientation_from_task_boundary_root_rpy_rad": [
        -0.0,
        0.0,
        -1e-06
      ],
      "name": "black_pawn_g_dynamic",
      "observed_spawn_yaw_range_rad": [
        -0.0,
        0.0
      ],
      "range_source": "observed_over_resets",
      "world_pose_after_reset": {
        "kind": "exact",
        "orientation_rpy_rad": [
          -0.0,
          0.0,
          0.108768
        ],
        "position_xyz_m": [
          0.315737,
          0.076928,
          0.802513
        ],
        "quaternion_xyzw": [
          -0.0,
          0.0,
          0.054357,
          0.998522
        ],
        "source": "exact_after_one_rlbench_reset"
      },
      "world_position_distribution": {
        "x_uniform_max_m": 0.432489,
        "x_uniform_min_m": 0.065451,
        "y_uniform_max_m": 0.274013,
        "y_uniform_min_m": -0.304304,
        "z_fixed_m": 0.802513
      }
    },
    {
      "fixed_offset_from_task_boundary_root_xyz_m": [
        0.167379,
        0.120794,
        0.050514
      ],
      "fixed_orientation_from_task_boundary_root_rpy_rad": [
        -0.0,
        0.0,
        -1e-06
      ],
      "name": "black_pawn_h_dynamic",
      "observed_spawn_yaw_range_rad": [
        -0.0,
        0.0
      ],
      "range_source": "observed_over_resets",
      "world_pose_after_reset": {
        "kind": "exact",
        "orientation_rpy_rad": [
          -0.0,
          0.0,
          0.108768
        ],
        "position_xyz_m": [
          0.363338,
          0.082125,
          0.802513
        ],
        "quaternion_xyzw": [
          -0.0,
          0.0,
          0.054357,
          0.998522
        ],
        "source": "exact_after_one_rlbench_reset"
      },
      "world_position_distribution": {
        "x_uniform_max_m": 0.469803,
        "x_uniform_min_m": 0.031128,
        "y_uniform_max_m": 0.310629,
        "y_uniform_min_m": -0.296582,
        "z_fixed_m": 0.802513
      }
    },
    {
      "fixed_offset_from_task_boundary_root_xyz_m": [
        -0.024156,
        0.168678,
        0.061043
      ],
      "fixed_orientation_from_task_boundary_root_rpy_rad": [
        0.0,
        0.0,
        -1e-06
      ],
      "name": "black_queen_dynamic",
      "observed_spawn_yaw_range_rad": [
        -0.0,
        0.0
      ],
      "range_source": "observed_over_resets",
      "world_pose_after_reset": {
        "kind": "exact",
        "orientation_rpy_rad": [
          0.0,
          0.0,
          0.108768
        ],
        "position_xyz_m": [
          0.167737,
          0.108934,
          0.813043
        ],
        "quaternion_xyzw": [
          0.0,
          0.0,
          0.054357,
          0.998522
        ],
        "source": "exact_after_one_rlbench_reset"
      },
      "world_position_distribution": {
        "x_uniform_max_m": 0.401749,
        "x_uniform_min_m": 0.061538,
        "y_uniform_max_m": 0.292006,
        "y_uniform_min_m": -0.374723,
        "z_fixed_m": 0.813043
      }
    },
    {
      "fixed_offset_from_task_boundary_root_xyz_m": [
        -0.072039,
        0.168678,
        0.058532
      ],
      "fixed_orientation_from_task_boundary_root_rpy_rad": [
        0.0,
        -0.0,
        -1e-06
      ],
      "name": "black_queenside_bishop_dynamic",
      "observed_spawn_yaw_range_rad": [
        -0.0,
        0.0
      ],
      "range_source": "observed_over_resets",
      "world_pose_after_reset": {
        "kind": "exact",
        "orientation_rpy_rad": [
          0.0,
          -0.0,
          0.108768
        ],
        "position_xyz_m": [
          0.120136,
          0.103736,
          0.810532
        ],
        "quaternion_xyzw": [
          0.0,
          -0.0,
          0.054357,
          0.998522
        ],
        "source": "exact_after_one_rlbench_reset"
      },
      "world_position_distribution": {
        "x_uniform_max_m": 0.426511,
        "x_uniform_min_m": 0.019427,
        "y_uniform_max_m": 0.314396,
        "y_uniform_min_m": -0.382445,
        "z_fixed_m": 0.810532
      }
    },
    {
      "fixed_offset_from_task_boundary_root_xyz_m": [
        -0.119924,
        0.168678,
        0.054934
      ],
      "fixed_orientation_from_task_boundary_root_rpy_rad": [
        -0.0,
        -0.0,
        -1e-06
      ],
      "name": "black_queenside_knight_dynamic",
      "observed_spawn_yaw_range_rad": [
        -0.0,
        0.0
      ],
      "range_source": "observed_over_resets",
      "world_pose_after_reset": {
        "kind": "exact",
        "orientation_rpy_rad": [
          -0.0,
          -0.0,
          0.108768
        ],
        "position_xyz_m": [
          0.072535,
          0.098538,
          0.806934
        ],
        "quaternion_xyzw": [
          -0.0,
          -0.0,
          0.054357,
          0.998522
        ],
        "source": "exact_after_one_rlbench_reset"
      },
      "world_position_distribution": {
        "x_uniform_max_m": 0.454088,
        "x_uniform_min_m": 0.010353,
        "y_uniform_max_m": 0.353992,
        "y_uniform_min_m": -0.390166,
        "z_fixed_m": 0.806934
      }
    },
    {
      "fixed_offset_from_task_boundary_root_xyz_m": [
        -0.167807,
        0.168677,
        0.046546
      ],
      "fixed_orientation_from_task_boundary_root_rpy_rad": [
        -0.0,
        0.0,
        -1e-06
      ],
      "name": "black_queenside_rook_dynamic",
      "observed_spawn_yaw_range_rad": [
        -0.0,
        0.0
      ],
      "range_source": "observed_over_resets",
      "world_pose_after_reset": {
        "kind": "exact",
        "orientation_rpy_rad": [
          -0.0,
          0.0,
          0.108768
        ],
        "position_xyz_m": [
          0.024934,
          0.093339,
          0.798546
        ],
        "quaternion_xyzw": [
          -0.0,
          0.0,
          0.054357,
          0.998522
        ],
        "source": "exact_after_one_rlbench_reset"
      },
      "world_position_distribution": {
        "x_uniform_max_m": 0.481663,
        "x_uniform_min_m": 0.001279,
        "y_uniform_max_m": 0.393587,
        "y_uniform_min_m": -0.397887,
        "z_fixed_m": 0.798546
      }
    }
  ],
  "other_scene_objects": [
    {
      "fixed_offset_from_reference_local_xyz_m": [
        -0.023962,
        -0.023951,
        -0.041734
      ],
      "fixed_offset_from_reference_xyz_m": [
        -0.02122,
        -0.026411,
        -0.041734
      ],
      "fixed_orientation_from_reference_rpy_rad": [
        0.0,
        0.0,
        1e-06
      ],
      "has_separate_distribution": false,
      "name": "chess_board_base",
      "reference_graspable_object": "black_pawn_e_dynamic",
      "world_pose_after_reset": {
        "kind": "exact",
        "orientation_rpy_rad": [
          -0.0,
          0.0,
          0.108769
        ],
        "position_xyz_m": [
          0.210061,
          -0.056125,
          0.76078
        ],
        "quaternion_xyzw": [
          0.0,
          0.0,
          0.054358,
          0.998522
        ],
        "source": "exact_after_one_rlbench_reset"
      },
      "world_position_range_due_to_task_root_sampling": {
        "x_uniform_max_m": 0.36562,
        "x_uniform_min_m": 0.18,
        "y_uniform_max_m": 0.24562,
        "y_uniform_min_m": -0.24562,
        "z_fixed_m": 0.76078
      }
    },
    {
      "fixed_offset_from_reference_local_xyz_m": [
        -0.024182,
        -0.022866,
        -0.030903
      ],
      "fixed_offset_from_reference_xyz_m": [
        -0.021557,
        -0.025356,
        -0.030903
      ],
      "fixed_orientation_from_reference_rpy_rad": [
        -0.0,
        0.0,
        1e-06
      ],
      "has_separate_distribution": false,
      "name": "chess_board_surface",
      "reference_graspable_object": "black_pawn_e_dynamic",
      "world_pose_after_reset": {
        "kind": "exact",
        "orientation_rpy_rad": [
          -0.0,
          0.0,
          0.108769
        ],
        "position_xyz_m": [
          0.209724,
          -0.05507,
          0.77161
        ],
        "quaternion_xyzw": [
          -0.0,
          0.0,
          0.054358,
          0.998522
        ],
        "source": "exact_after_one_rlbench_reset"
      },
      "world_position_range_due_to_task_root_sampling": {
        "x_uniform_max_m": 0.366727,
        "x_uniform_min_m": 0.178893,
        "y_uniform_max_m": 0.246727,
        "y_uniform_min_m": -0.246727,
        "z_fixed_m": 0.77161
      }
    },
    {
      "fixed_offset_from_reference_local_xyz_m": [
        -0.024177,
        -0.022866,
        -0.030898
      ],
      "fixed_offset_from_reference_xyz_m": [
        -0.021552,
        -0.025355,
        -0.030898
      ],
      "fixed_orientation_from_reference_rpy_rad": [
        -1.570796,
        -1e-06,
        -1.570796
      ],
      "has_separate_distribution": false,
      "name": "white_squares",
      "reference_graspable_object": "black_pawn_e_dynamic",
      "world_pose_after_reset": {
        "kind": "exact",
        "orientation_rpy_rad": [
          -1.570796,
          -0.108769,
          -1.570796
        ],
        "position_xyz_m": [
          0.209729,
          -0.05507,
          0.771616
        ],
        "quaternion_xyzw": [
          -0.472082,
          -0.52644,
          -0.472082,
          0.52644
        ],
        "source": "exact_after_one_rlbench_reset"
      },
      "world_position_range_due_to_task_root_sampling": {
        "x_uniform_max_m": 0.366726,
        "x_uniform_min_m": 0.178894,
        "y_uniform_max_m": 0.246726,
        "y_uniform_min_m": -0.246726,
        "z_fixed_m": 0.771616
      }
    },
    {
      "fixed_offset_from_reference_local_xyz_m": [
        -0.024177,
        -0.022866,
        -0.030896
      ],
      "fixed_offset_from_reference_xyz_m": [
        -0.021552,
        -0.025355,
        -0.030896
      ],
      "fixed_orientation_from_reference_rpy_rad": [
        0.0,
        -1.570796,
        -0.0
      ],
      "has_separate_distribution": false,
      "name": "black_squares",
      "reference_graspable_object": "black_pawn_e_dynamic",
      "world_pose_after_reset": {
        "kind": "exact",
        "orientation_rpy_rad": [
          1.570796,
          -1.462027,
          1.570796
        ],
        "position_xyz_m": [
          0.209729,
          -0.05507,
          0.771618
        ],
        "quaternion_xyzw": [
          0.038437,
          -0.706061,
          0.038437,
          0.706061
        ],
        "source": "exact_after_one_rlbench_reset"
      },
      "world_position_range_due_to_task_root_sampling": {
        "x_uniform_max_m": 0.366726,
        "x_uniform_min_m": 0.178894,
        "y_uniform_max_m": 0.246726,
        "y_uniform_min_m": -0.246726,
        "z_fixed_m": 0.771618
      }
    },
    {
      "fixed_offset_from_reference_local_xyz_m": [
        0.0,
        0.0,
        0.0
      ],
      "fixed_offset_from_reference_xyz_m": [
        0.0,
        0.0,
        0.0
      ],
      "fixed_orientation_from_reference_rpy_rad": [
        -1.5e-05,
        -1.5e-05,
        -1e-06
      ],
      "has_separate_distribution": false,
      "mounted_on_graspable": "white_queenside_knight_dynamic",
      "name": "white_queenside_knight",
      "reference_graspable_object": "white_queenside_knight_dynamic",
      "rotation_radius_from_graspable_m": 0.0,
      "spawn_rotation_note": "Mounted on graspable 'white_queenside_knight_dynamic', which RLBench randomly positions and yaw-rotates (+/-pi) each episode; world range is the 'white_queenside_knight_dynamic' observed envelope expanded by the mount radius.",
      "world_pose_after_reset": {
        "kind": "exact",
        "orientation_rpy_rad": [
          -1.3e-05,
          -1.6e-05,
          0.108768
        ],
        "position_xyz_m": [
          0.108918,
          -0.234661,
          0.806934
        ],
        "quaternion_xyzw": [
          -7e-06,
          -8e-06,
          0.054357,
          0.998522
        ],
        "source": "exact_after_one_rlbench_reset"
      },
      "world_position_range_due_to_task_root_sampling": {
        "kind": "mounted_on_graspable_envelope",
        "mounted_on_graspable": "white_queenside_knight_dynamic",
        "n_resets_observed": 30,
        "rotation_radius_m": 0.0,
        "source": "observed_white_queenside_knight_dynamic_range_expanded_by_mount_radius_for_full_yaw",
        "x_uniform_max_m": 0.51172,
        "x_uniform_min_m": -0.020796,
        "y_uniform_max_m": 0.398001,
        "y_uniform_min_m": -0.296375,
        "z_fixed_m": 0.806934
      }
    },
    {
      "fixed_offset_from_reference_local_xyz_m": [
        0.0,
        0.0,
        0.0
      ],
      "fixed_offset_from_reference_xyz_m": [
        0.0,
        0.0,
        0.0
      ],
      "fixed_orientation_from_reference_rpy_rad": [
        -1.5e-05,
        -1.5e-05,
        -1e-06
      ],
      "has_separate_distribution": false,
      "mounted_on_graspable": "white_kingside_knight_dynamic",
      "name": "white_kingside_knight",
      "reference_graspable_object": "white_kingside_knight_dynamic",
      "rotation_radius_from_graspable_m": 0.0,
      "spawn_rotation_note": "Mounted on graspable 'white_kingside_knight_dynamic', which RLBench randomly positions and yaw-rotates (+/-pi) each episode; world range is the 'white_kingside_knight_dynamic' observed envelope expanded by the mount radius.",
      "world_pose_after_reset": {
        "kind": "exact",
        "orientation_rpy_rad": [
          -1.3e-05,
          -1.6e-05,
          0.108768
        ],
        "position_xyz_m": [
          0.346924,
          -0.208677,
          0.806934
        ],
        "quaternion_xyzw": [
          -7e-06,
          -8e-06,
          0.054357,
          0.998522
        ],
        "source": "exact_after_one_rlbench_reset"
      },
      "world_position_range_due_to_task_root_sampling": {
        "kind": "mounted_on_graspable_envelope",
        "mounted_on_graspable": "white_kingside_knight_dynamic",
        "n_resets_observed": 30,
        "rotation_radius_m": 0.0,
        "source": "observed_white_kingside_knight_dynamic_range_expanded_by_mount_radius_for_full_yaw",
        "x_uniform_max_m": 0.491178,
        "x_uniform_min_m": -0.008969,
        "y_uniform_max_m": 0.390305,
        "y_uniform_min_m": -0.300516,
        "z_fixed_m": 0.806934
      }
    },
    {
      "fixed_offset_from_reference_local_xyz_m": [
        0.0,
        0.0,
        0.0
      ],
      "fixed_offset_from_reference_xyz_m": [
        0.0,
        0.0,
        0.0
      ],
      "fixed_orientation_from_reference_rpy_rad": [
        -0.0,
        0.0,
        -0.0
      ],
      "has_separate_distribution": false,
      "mounted_on_graspable": "white_pawn_a_dynamic",
      "name": "white_pawn_a",
      "reference_graspable_object": "white_pawn_a_dynamic",
      "rotation_radius_from_graspable_m": 0.0,
      "spawn_rotation_note": "Mounted on graspable 'white_pawn_a_dynamic', which RLBench randomly positions and yaw-rotates (+/-pi) each episode; world range is the 'white_pawn_a_dynamic' observed envelope expanded by the mount radius.",
      "world_pose_after_reset": {
        "kind": "exact",
        "orientation_rpy_rad": [
          -0.0,
          0.0,
          0.108768
        ],
        "position_xyz_m": [
          0.056123,
          -0.192264,
          0.802513
        ],
        "quaternion_xyzw": [
          -0.0,
          0.0,
          0.054357,
          0.998522
        ],
        "source": "exact_after_one_rlbench_reset"
      },
      "world_position_range_due_to_task_root_sampling": {
        "kind": "mounted_on_graspable_envelope",
        "mounted_on_graspable": "white_pawn_a_dynamic",
        "n_resets_observed": 30,
        "rotation_radius_m": 0.0,
        "source": "observed_white_pawn_a_dynamic_range_expanded_by_mount_radius_for_full_yaw",
        "x_uniform_max_m": 0.468129,
        "x_uniform_min_m": 0.024656,
        "y_uniform_max_m": 0.361035,
        "y_uniform_min_m": -0.334315,
        "z_fixed_m": 0.802513
      }
    },
    {
      "fixed_offset_from_reference_local_xyz_m": [
        0.0,
        0.0,
        0.0
      ],
      "fixed_offset_from_reference_xyz_m": [
        0.0,
        0.0,
        0.0
      ],
      "fixed_orientation_from_reference_rpy_rad": [
        -0.0,
        0.0,
        -0.0
      ],
      "has_separate_distribution": false,
      "mounted_on_graspable": "white_pawn_b_dynamic",
      "name": "white_pawn_b",
      "reference_graspable_object": "white_pawn_b_dynamic",
      "rotation_radius_from_graspable_m": 0.0,
      "spawn_rotation_note": "Mounted on graspable 'white_pawn_b_dynamic', which RLBench randomly positions and yaw-rotates (+/-pi) each episode; world range is the 'white_pawn_b_dynamic' observed envelope expanded by the mount radius.",
      "world_pose_after_reset": {
        "kind": "exact",
        "orientation_rpy_rad": [
          0.0,
          -0.0,
          0.108768
        ],
        "position_xyz_m": [
          0.103723,
          -0.187066,
          0.802513
        ],
        "quaternion_xyzw": [
          0.0,
          -0.0,
          0.054357,
          0.998522
        ],
        "source": "exact_after_one_rlbench_reset"
      },
      "world_position_range_due_to_task_root_sampling": {
        "kind": "mounted_on_graspable_envelope",
        "mounted_on_graspable": "white_pawn_b_dynamic",
        "n_resets_observed": 30,
        "rotation_radius_m": 0.0,
        "source": "observed_white_pawn_b_dynamic_range_expanded_by_mount_radius_for_full_yaw",
        "x_uniform_max_m": 0.464019,
        "x_uniform_min_m": 0.027023,
        "y_uniform_max_m": 0.350148,
        "y_uniform_min_m": -0.287299,
        "z_fixed_m": 0.802513
      }
    },
    {
      "fixed_offset_from_reference_local_xyz_m": [
        0.0,
        0.0,
        0.0
      ],
      "fixed_offset_from_reference_xyz_m": [
        0.0,
        0.0,
        0.0
      ],
      "fixed_orientation_from_reference_rpy_rad": [
        -0.0,
        0.0,
        -0.0
      ],
      "has_separate_distribution": false,
      "mounted_on_graspable": "white_pawn_c_dynamic",
      "name": "white_pawn_c",
      "reference_graspable_object": "white_pawn_c_dynamic",
      "rotation_radius_from_graspable_m": 0.0,
      "spawn_rotation_note": "Mounted on graspable 'white_pawn_c_dynamic', which RLBench randomly positions and yaw-rotates (+/-pi) each episode; world range is the 'white_pawn_c_dynamic' observed envelope expanded by the mount radius.",
      "world_pose_after_reset": {
        "kind": "exact",
        "orientation_rpy_rad": [
          -0.0,
          0.0,
          0.108768
        ],
        "position_xyz_m": [
          0.151324,
          -0.181868,
          0.802513
        ],
        "quaternion_xyzw": [
          -0.0,
          0.0,
          0.054357,
          0.998522
        ],
        "source": "exact_after_one_rlbench_reset"
      },
      "world_position_range_due_to_task_root_sampling": {
        "kind": "mounted_on_graspable_envelope",
        "mounted_on_graspable": "white_pawn_c_dynamic",
        "n_resets_observed": 30,
        "rotation_radius_m": 0.0,
        "source": "observed_white_pawn_c_dynamic_range_expanded_by_mount_radius_for_full_yaw",
        "x_uniform_max_m": 0.45991,
        "x_uniform_min_m": 0.029389,
        "y_uniform_max_m": 0.348608,
        "y_uniform_min_m": -0.240283,
        "z_fixed_m": 0.802513
      }
    },
    {
      "fixed_offset_from_reference_local_xyz_m": [
        0.0,
        0.0,
        0.0
      ],
      "fixed_offset_from_reference_xyz_m": [
        0.0,
        0.0,
        0.0
      ],
      "fixed_orientation_from_reference_rpy_rad": [
        -0.0,
        0.0,
        -0.0
      ],
      "has_separate_distribution": false,
      "mounted_on_graspable": "white_pawn_d_dynamic",
      "name": "white_pawn_d",
      "reference_graspable_object": "white_pawn_d_dynamic",
      "rotation_radius_from_graspable_m": 0.0,
      "spawn_rotation_note": "Mounted on graspable 'white_pawn_d_dynamic', which RLBench randomly positions and yaw-rotates (+/-pi) each episode; world range is the 'white_pawn_d_dynamic' observed envelope expanded by the mount radius.",
      "world_pose_after_reset": {
        "kind": "exact",
        "orientation_rpy_rad": [
          0.0,
          0.0,
          0.108768
        ],
        "position_xyz_m": [
          0.198924,
          -0.17667,
          0.802513
        ],
        "quaternion_xyzw": [
          0.0,
          -0.0,
          0.054357,
          0.998522
        ],
        "source": "exact_after_one_rlbench_reset"
      },
      "world_position_range_due_to_task_root_sampling": {
        "kind": "mounted_on_graspable_envelope",
        "mounted_on_graspable": "white_pawn_d_dynamic",
        "n_resets_observed": 30,
        "rotation_radius_m": 0.0,
        "source": "observed_white_pawn_d_dynamic_range_expanded_by_mount_radius_for_full_yaw",
        "x_uniform_max_m": 0.4558,
        "x_uniform_min_m": 0.031756,
        "y_uniform_max_m": 0.347068,
        "y_uniform_min_m": -0.218583,
        "z_fixed_m": 0.802513
      }
    },
    {
      "fixed_offset_from_reference_local_xyz_m": [
        0.0,
        0.0,
        0.0
      ],
      "fixed_offset_from_reference_xyz_m": [
        0.0,
        0.0,
        0.0
      ],
      "fixed_orientation_from_reference_rpy_rad": [
        -0.0,
        0.0,
        -0.0
      ],
      "has_separate_distribution": false,
      "mounted_on_graspable": "white_pawn_e_dynamic",
      "name": "white_pawn_e",
      "reference_graspable_object": "white_pawn_e_dynamic",
      "rotation_radius_from_graspable_m": 0.0,
      "spawn_rotation_note": "Mounted on graspable 'white_pawn_e_dynamic', which RLBench randomly positions and yaw-rotates (+/-pi) each episode; world range is the 'white_pawn_e_dynamic' observed envelope expanded by the mount radius.",
      "world_pose_after_reset": {
        "kind": "exact",
        "orientation_rpy_rad": [
          -0.0,
          -0.0,
          0.108768
        ],
        "position_xyz_m": [
          0.246525,
          -0.171472,
          0.802513
        ],
        "quaternion_xyzw": [
          -0.0,
          -0.0,
          0.054357,
          0.998522
        ],
        "source": "exact_after_one_rlbench_reset"
      },
      "world_position_range_due_to_task_root_sampling": {
        "kind": "mounted_on_graspable_envelope",
        "mounted_on_graspable": "white_pawn_e_dynamic",
        "n_resets_observed": 30,
        "rotation_radius_m": 0.0,
        "source": "observed_white_pawn_e_dynamic_range_expanded_by_mount_radius_for_full_yaw",
        "x_uniform_max_m": 0.451691,
        "x_uniform_min_m": 0.034123,
        "y_uniform_max_m": 0.345527,
        "y_uniform_min_m": -0.224269,
        "z_fixed_m": 0.802513
      }
    },
    {
      "fixed_offset_from_reference_local_xyz_m": [
        0.0,
        0.0,
        0.0
      ],
      "fixed_offset_from_reference_xyz_m": [
        0.0,
        0.0,
        0.0
      ],
      "fixed_orientation_from_reference_rpy_rad": [
        -0.0,
        0.0,
        -0.0
      ],
      "has_separate_distribution": false,
      "mounted_on_graspable": "white_pawn_f_dynamic",
      "name": "white_pawn_f",
      "reference_graspable_object": "white_pawn_f_dynamic",
      "rotation_radius_from_graspable_m": 0.0,
      "spawn_rotation_note": "Mounted on graspable 'white_pawn_f_dynamic', which RLBench randomly positions and yaw-rotates (+/-pi) each episode; world range is the 'white_pawn_f_dynamic' observed envelope expanded by the mount radius.",
      "world_pose_after_reset": {
        "kind": "exact",
        "orientation_rpy_rad": [
          0.0,
          0.0,
          0.108768
        ],
        "position_xyz_m": [
          0.294126,
          -0.166274,
          0.802513
        ],
        "quaternion_xyzw": [
          0.0,
          0.0,
          0.054357,
          0.998522
        ],
        "source": "exact_after_one_rlbench_reset"
      },
      "world_position_range_due_to_task_root_sampling": {
        "kind": "mounted_on_graspable_envelope",
        "mounted_on_graspable": "white_pawn_f_dynamic",
        "n_resets_observed": 30,
        "rotation_radius_m": 0.0,
        "source": "observed_white_pawn_f_dynamic_range_expanded_by_mount_radius_for_full_yaw",
        "x_uniform_max_m": 0.447581,
        "x_uniform_min_m": 0.03649,
        "y_uniform_max_m": 0.343986,
        "y_uniform_min_m": -0.239733,
        "z_fixed_m": 0.802513
      }
    },
    {
      "fixed_offset_from_reference_local_xyz_m": [
        0.0,
        0.0,
        0.0
      ],
      "fixed_offset_from_reference_xyz_m": [
        0.0,
        0.0,
        0.0
      ],
      "fixed_orientation_from_reference_rpy_rad": [
        -0.0,
        0.0,
        -0.0
      ],
      "has_separate_distribution": false,
      "mounted_on_graspable": "white_pawn_g_dynamic",
      "name": "white_pawn_g",
      "reference_graspable_object": "white_pawn_g_dynamic",
      "rotation_radius_from_graspable_m": 0.0,
      "spawn_rotation_note": "Mounted on graspable 'white_pawn_g_dynamic', which RLBench randomly positions and yaw-rotates (+/-pi) each episode; world range is the 'white_pawn_g_dynamic' observed envelope expanded by the mount radius.",
      "world_pose_after_reset": {
        "kind": "exact",
        "orientation_rpy_rad": [
          0.0,
          -0.0,
          0.108768
        ],
        "position_xyz_m": [
          0.341727,
          -0.161077,
          0.802513
        ],
        "quaternion_xyzw": [
          0.0,
          -0.0,
          0.054357,
          0.998522
        ],
        "source": "exact_after_one_rlbench_reset"
      },
      "world_position_range_due_to_task_root_sampling": {
        "kind": "mounted_on_graspable_envelope",
        "mounted_on_graspable": "white_pawn_g_dynamic",
        "n_resets_observed": 30,
        "rotation_radius_m": 0.0,
        "source": "observed_white_pawn_g_dynamic_range_expanded_by_mount_radius_for_full_yaw",
        "x_uniform_max_m": 0.443472,
        "x_uniform_min_m": 0.038856,
        "y_uniform_max_m": 0.342446,
        "y_uniform_min_m": -0.255199,
        "z_fixed_m": 0.802513
      }
    },
    {
      "fixed_offset_from_reference_local_xyz_m": [
        0.0,
        0.0,
        0.0
      ],
      "fixed_offset_from_reference_xyz_m": [
        0.0,
        0.0,
        0.0
      ],
      "fixed_orientation_from_reference_rpy_rad": [
        -0.0,
        0.0,
        -0.0
      ],
      "has_separate_distribution": false,
      "mounted_on_graspable": "white_pawn_h_dynamic",
      "name": "white_pawn_h",
      "reference_graspable_object": "white_pawn_h_dynamic",
      "rotation_radius_from_graspable_m": 0.0,
      "spawn_rotation_note": "Mounted on graspable 'white_pawn_h_dynamic', which RLBench randomly positions and yaw-rotates (+/-pi) each episode; world range is the 'white_pawn_h_dynamic' observed envelope expanded by the mount radius.",
      "world_pose_after_reset": {
        "kind": "exact",
        "orientation_rpy_rad": [
          -0.0,
          0.0,
          0.108768
        ],
        "position_xyz_m": [
          0.389327,
          -0.155878,
          0.802513
        ],
        "quaternion_xyzw": [
          -0.0,
          0.0,
          0.054357,
          0.998522
        ],
        "source": "exact_after_one_rlbench_reset"
      },
      "world_position_range_due_to_task_root_sampling": {
        "kind": "mounted_on_graspable_envelope",
        "mounted_on_graspable": "white_pawn_h_dynamic",
        "n_resets_observed": 30,
        "rotation_radius_m": 0.0,
        "source": "observed_white_pawn_h_dynamic_range_expanded_by_mount_radius_for_full_yaw",
        "x_uniform_max_m": 0.449388,
        "x_uniform_min_m": -0.005736,
        "y_uniform_max_m": 0.340905,
        "y_uniform_min_m": -0.270663,
        "z_fixed_m": 0.802513
      }
    },
    {
      "fixed_offset_from_reference_local_xyz_m": [
        0.0,
        0.0,
        0.0
      ],
      "fixed_offset_from_reference_xyz_m": [
        0.0,
        0.0,
        0.0
      ],
      "fixed_orientation_from_reference_rpy_rad": [
        -0.0,
        0.0,
        0.0
      ],
      "has_separate_distribution": false,
      "mounted_on_graspable": "white_queenside_rook_dynamic",
      "name": "white_queenside_rook",
      "reference_graspable_object": "white_queenside_rook_dynamic",
      "rotation_radius_from_graspable_m": 0.0,
      "spawn_rotation_note": "Mounted on graspable 'white_queenside_rook_dynamic', which RLBench randomly positions and yaw-rotates (+/-pi) each episode; world range is the 'white_queenside_rook_dynamic' observed envelope expanded by the mount radius.",
      "world_pose_after_reset": {
        "kind": "exact",
        "orientation_rpy_rad": [
          0.0,
          -0.0,
          0.108768
        ],
        "position_xyz_m": [
          0.061197,
          -0.238759,
          0.798546
        ],
        "quaternion_xyzw": [
          0.0,
          -0.0,
          0.054357,
          0.998522
        ],
        "source": "exact_after_one_rlbench_reset"
      },
      "world_position_range_due_to_task_root_sampling": {
        "kind": "mounted_on_graspable_envelope",
        "mounted_on_graspable": "white_queenside_rook_dynamic",
        "n_resets_observed": 30,
        "rotation_radius_m": 0.0,
        "source": "observed_white_queenside_rook_dynamic_range_expanded_by_mount_radius_for_full_yaw",
        "x_uniform_max_m": 0.514727,
        "x_uniform_min_m": -0.022057,
        "y_uniform_max_m": 0.398436,
        "y_uniform_min_m": -0.34318,
        "z_fixed_m": 0.798546
      }
    },
    {
      "fixed_offset_from_reference_local_xyz_m": [
        0.0,
        0.0,
        0.0
      ],
      "fixed_offset_from_reference_xyz_m": [
        0.0,
        0.0,
        0.0
      ],
      "fixed_orientation_from_reference_rpy_rad": [
        -0.0,
        -0.0,
        0.0
      ],
      "has_separate_distribution": false,
      "mounted_on_graspable": "white_kingside_rook_dynamic",
      "name": "white_kingside_rook",
      "reference_graspable_object": "white_kingside_rook_dynamic",
      "rotation_radius_from_graspable_m": 0.0,
      "spawn_rotation_note": "Mounted on graspable 'white_kingside_rook_dynamic', which RLBench randomly positions and yaw-rotates (+/-pi) each episode; world range is the 'white_kingside_rook_dynamic' observed envelope expanded by the mount radius.",
      "world_pose_after_reset": {
        "kind": "exact",
        "orientation_rpy_rad": [
          0.0,
          0.0,
          0.108768
        ],
        "position_xyz_m": [
          0.394526,
          -0.203467,
          0.798546
        ],
        "quaternion_xyzw": [
          0.0,
          -0.0,
          0.054357,
          0.998522
        ],
        "source": "exact_after_one_rlbench_reset"
      },
      "world_position_range_due_to_task_root_sampling": {
        "kind": "mounted_on_graspable_envelope",
        "mounted_on_graspable": "white_kingside_rook_dynamic",
        "n_resets_observed": 30,
        "rotation_radius_m": 0.0,
        "source": "observed_white_kingside_rook_dynamic_range_expanded_by_mount_radius_for_full_yaw",
        "x_uniform_max_m": 0.491616,
        "x_uniform_min_m": -0.016924,
        "y_uniform_max_m": 0.388753,
        "y_uniform_min_m": -0.315971,
        "z_fixed_m": 0.798546
      }
    },
    {
      "fixed_offset_from_reference_local_xyz_m": [
        0.0,
        0.0,
        0.0
      ],
      "fixed_offset_from_reference_xyz_m": [
        0.0,
        0.0,
        0.0
      ],
      "fixed_orientation_from_reference_rpy_rad": [
        -0.0,
        0.0,
        -0.0
      ],
      "has_separate_distribution": false,
      "mounted_on_graspable": "white_queenside_bishop_dynamic",
      "name": "white_queenside_bishop",
      "reference_graspable_object": "white_queenside_bishop_dynamic",
      "rotation_radius_from_graspable_m": 0.0,
      "spawn_rotation_note": "Mounted on graspable 'white_queenside_bishop_dynamic', which RLBench randomly positions and yaw-rotates (+/-pi) each episode; world range is the 'white_queenside_bishop_dynamic' observed envelope expanded by the mount radius.",
      "world_pose_after_reset": {
        "kind": "exact",
        "orientation_rpy_rad": [
          -0.0,
          0.0,
          0.108768
        ],
        "position_xyz_m": [
          0.156521,
          -0.229469,
          0.810532
        ],
        "quaternion_xyzw": [
          -0.0,
          0.0,
          0.054357,
          0.998522
        ],
        "source": "exact_after_one_rlbench_reset"
      },
      "world_position_range_due_to_task_root_sampling": {
        "kind": "mounted_on_graspable_envelope",
        "mounted_on_graspable": "white_queenside_bishop_dynamic",
        "n_resets_observed": 30,
        "rotation_radius_m": 0.0,
        "source": "observed_white_queenside_bishop_dynamic_range_expanded_by_mount_radius_for_full_yaw",
        "x_uniform_max_m": 0.507617,
        "x_uniform_min_m": -0.018436,
        "y_uniform_max_m": 0.396467,
        "y_uniform_min_m": -0.263601,
        "z_fixed_m": 0.810532
      }
    },
    {
      "fixed_offset_from_reference_local_xyz_m": [
        0.0,
        0.0,
        0.0
      ],
      "fixed_offset_from_reference_xyz_m": [
        0.0,
        0.0,
        0.0
      ],
      "fixed_orientation_from_reference_rpy_rad": [
        -0.0,
        0.0,
        -0.0
      ],
      "has_separate_distribution": false,
      "mounted_on_graspable": "white_kingside_bishop_dynamic",
      "name": "white_kingside_bishop",
      "reference_graspable_object": "white_kingside_bishop_dynamic",
      "rotation_radius_from_graspable_m": 0.0,
      "spawn_rotation_note": "Mounted on graspable 'white_kingside_bishop_dynamic', which RLBench randomly positions and yaw-rotates (+/-pi) each episode; world range is the 'white_kingside_bishop_dynamic' observed envelope expanded by the mount radius.",
      "world_pose_after_reset": {
        "kind": "exact",
        "orientation_rpy_rad": [
          0.0,
          0.0,
          0.108768
        ],
        "position_xyz_m": [
          0.299324,
          -0.213875,
          0.810532
        ],
        "quaternion_xyzw": [
          0.0,
          0.0,
          0.054357,
          0.998522
        ],
        "source": "exact_after_one_rlbench_reset"
      },
      "world_position_range_due_to_task_root_sampling": {
        "kind": "mounted_on_graspable_envelope",
        "mounted_on_graspable": "white_kingside_bishop_dynamic",
        "n_resets_observed": 30,
        "rotation_radius_m": 0.0,
        "source": "observed_white_kingside_bishop_dynamic_range_expanded_by_mount_radius_for_full_yaw",
        "x_uniform_max_m": 0.495288,
        "x_uniform_min_m": -0.011336,
        "y_uniform_max_m": 0.391845,
        "y_uniform_min_m": -0.271954,
        "z_fixed_m": 0.810532
      }
    },
    {
      "fixed_offset_from_reference_local_xyz_m": [
        0.0,
        0.0,
        0.0
      ],
      "fixed_offset_from_reference_xyz_m": [
        0.0,
        0.0,
        0.0
      ],
      "fixed_orientation_from_reference_rpy_rad": [
        -0.0,
        0.0,
        -0.0
      ],
      "has_separate_distribution": false,
      "mounted_on_graspable": "white_queen_dynamic",
      "name": "white_queen",
      "reference_graspable_object": "white_queen_dynamic",
      "rotation_radius_from_graspable_m": 0.0,
      "spawn_rotation_note": "Mounted on graspable 'white_queen_dynamic', which RLBench randomly positions and yaw-rotates (+/-pi) each episode; world range is the 'white_queen_dynamic' observed envelope expanded by the mount radius.",
      "world_pose_after_reset": {
        "kind": "exact",
        "orientation_rpy_rad": [
          0.0,
          0.0,
          0.108768
        ],
        "position_xyz_m": [
          0.204071,
          -0.224256,
          0.813043
        ],
        "quaternion_xyzw": [
          0.0,
          0.0,
          0.054357,
          0.998522
        ],
        "source": "exact_after_one_rlbench_reset"
      },
      "world_position_range_due_to_task_root_sampling": {
        "kind": "mounted_on_graspable_envelope",
        "mounted_on_graspable": "white_queen_dynamic",
        "n_resets_observed": 30,
        "rotation_radius_m": 0.0,
        "source": "observed_white_queen_dynamic_range_expanded_by_mount_radius_for_full_yaw",
        "x_uniform_max_m": 0.503491,
        "x_uniform_min_m": -0.016051,
        "y_uniform_max_m": 0.394908,
        "y_uniform_min_m": -0.266362,
        "z_fixed_m": 0.813043
      }
    },
    {
      "fixed_offset_from_reference_local_xyz_m": [
        0.0,
        0.0,
        0.0
      ],
      "fixed_offset_from_reference_xyz_m": [
        0.0,
        0.0,
        0.0
      ],
      "fixed_orientation_from_reference_rpy_rad": [
        3.141383,
        -0.000275,
        1.570797
      ],
      "has_separate_distribution": false,
      "mounted_on_graspable": "white_king_dynamic",
      "name": "white_king",
      "reference_graspable_object": "white_king_dynamic",
      "rotation_radius_from_graspable_m": 0.0,
      "spawn_rotation_note": "Mounted on graspable 'white_king_dynamic', which RLBench randomly positions and yaw-rotates (+/-pi) each episode; world range is the 'white_king_dynamic' observed envelope expanded by the mount radius.",
      "world_pose_after_reset": {
        "kind": "exact",
        "orientation_rpy_rad": [
          3.141354,
          -0.000251,
          1.462028
        ],
        "position_xyz_m": [
          0.251611,
          -0.217984,
          0.815519
        ],
        "quaternion_xyzw": [
          0.744498,
          -0.667625,
          -1.4e-05,
          0.000172
        ],
        "source": "exact_after_one_rlbench_reset"
      },
      "world_position_range_due_to_task_root_sampling": {
        "kind": "mounted_on_graspable_envelope",
        "mounted_on_graspable": "white_king_dynamic",
        "n_resets_observed": 30,
        "rotation_radius_m": 0.0,
        "source": "observed_white_king_dynamic_range_expanded_by_mount_radius_for_full_yaw",
        "x_uniform_max_m": 0.498306,
        "x_uniform_min_m": -0.012609,
        "y_uniform_max_m": 0.260438,
        "y_uniform_min_m": -0.268553,
        "z_fixed_m": 0.815519
      }
    },
    {
      "fixed_offset_from_reference_local_xyz_m": [
        0.0,
        0.0,
        0.0
      ],
      "fixed_offset_from_reference_xyz_m": [
        0.0,
        0.0,
        0.0
      ],
      "fixed_orientation_from_reference_rpy_rad": [
        -0.0,
        0.000369,
        -3.141592
      ],
      "has_separate_distribution": false,
      "mounted_on_graspable": "black_queenside_knight_dynamic",
      "name": "black_queenside_knight",
      "reference_graspable_object": "black_queenside_knight_dynamic",
      "rotation_radius_from_graspable_m": 0.0,
      "spawn_rotation_note": "Mounted on graspable 'black_queenside_knight_dynamic', which RLBench randomly positions and yaw-rotates (+/-pi) each episode; world range is the 'black_queenside_knight_dynamic' observed envelope expanded by the mount radius.",
      "world_pose_after_reset": {
        "kind": "exact",
        "orientation_rpy_rad": [
          -4e-05,
          0.000367,
          -3.032824
        ],
        "position_xyz_m": [
          0.072535,
          0.098538,
          0.806934
        ],
        "quaternion_xyzw": [
          0.000184,
          1e-05,
          0.998522,
          -0.054358
        ],
        "source": "exact_after_one_rlbench_reset"
      },
      "world_position_range_due_to_task_root_sampling": {
        "kind": "mounted_on_graspable_envelope",
        "mounted_on_graspable": "black_queenside_knight_dynamic",
        "n_resets_observed": 30,
        "rotation_radius_m": 0.0,
        "source": "observed_black_queenside_knight_dynamic_range_expanded_by_mount_radius_for_full_yaw",
        "x_uniform_max_m": 0.454088,
        "x_uniform_min_m": 0.010353,
        "y_uniform_max_m": 0.353992,
        "y_uniform_min_m": -0.390166,
        "z_fixed_m": 0.806934
      }
    },
    {
      "fixed_offset_from_reference_local_xyz_m": [
        0.0,
        0.0,
        0.0
      ],
      "fixed_offset_from_reference_xyz_m": [
        0.0,
        0.0,
        0.0
      ],
      "fixed_orientation_from_reference_rpy_rad": [
        -0.0,
        0.000372,
        -3.141593
      ],
      "has_separate_distribution": false,
      "mounted_on_graspable": "black_kingside_knight_dynamic",
      "name": "black_kingside_knight",
      "reference_graspable_object": "black_kingside_knight_dynamic",
      "rotation_radius_from_graspable_m": 0.0,
      "spawn_rotation_note": "Mounted on graspable 'black_kingside_knight_dynamic', which RLBench randomly positions and yaw-rotates (+/-pi) each episode; world range is the 'black_kingside_knight_dynamic' observed envelope expanded by the mount radius.",
      "world_pose_after_reset": {
        "kind": "exact",
        "orientation_rpy_rad": [
          -4e-05,
          0.00037,
          -3.032824
        ],
        "position_xyz_m": [
          0.310539,
          0.124527,
          0.806934
        ],
        "quaternion_xyzw": [
          0.000186,
          1e-05,
          0.998522,
          -0.054357
        ],
        "source": "exact_after_one_rlbench_reset"
      },
      "world_position_range_due_to_task_root_sampling": {
        "kind": "mounted_on_graspable_envelope",
        "mounted_on_graspable": "black_kingside_knight_dynamic",
        "n_resets_observed": 30,
        "rotation_radius_m": 0.0,
        "source": "observed_black_kingside_knight_dynamic_range_expanded_by_mount_radius_for_full_yaw",
        "x_uniform_max_m": 0.472084,
        "x_uniform_min_m": 0.031064,
        "y_uniform_max_m": 0.30487,
        "y_uniform_min_m": -0.35156,
        "z_fixed_m": 0.806934
      }
    },
    {
      "fixed_offset_from_reference_local_xyz_m": [
        0.0,
        0.0,
        0.0
      ],
      "fixed_offset_from_reference_xyz_m": [
        0.0,
        0.0,
        0.0
      ],
      "fixed_orientation_from_reference_rpy_rad": [
        0.000345,
        2.6e-05,
        1.570796
      ],
      "has_separate_distribution": false,
      "mounted_on_graspable": "black_pawn_f_dynamic",
      "name": "black_pawn_f",
      "reference_graspable_object": "black_pawn_f_dynamic",
      "rotation_radius_from_graspable_m": 0.0,
      "spawn_rotation_note": "Mounted on graspable 'black_pawn_f_dynamic', which RLBench randomly positions and yaw-rotates (+/-pi) each episode; world range is the 'black_pawn_f_dynamic' observed envelope expanded by the mount radius.",
      "world_pose_after_reset": {
        "kind": "exact",
        "orientation_rpy_rad": [
          0.00034,
          6.4e-05,
          1.679565
        ],
        "position_xyz_m": [
          0.268137,
          0.071729,
          0.802513
        ],
        "quaternion_xyzw": [
          0.000137,
          -0.000105,
          0.744498,
          0.667625
        ],
        "source": "exact_after_one_rlbench_reset"
      },
      "world_position_range_due_to_task_root_sampling": {
        "kind": "mounted_on_graspable_envelope",
        "mounted_on_graspable": "black_pawn_f_dynamic",
        "n_resets_observed": 30,
        "rotation_radius_m": 0.0,
        "source": "observed_black_pawn_f_dynamic_range_expanded_by_mount_radius_for_full_yaw",
        "x_uniform_max_m": 0.405562,
        "x_uniform_min_m": 0.079414,
        "y_uniform_max_m": 0.240037,
        "y_uniform_min_m": -0.231854,
        "z_fixed_m": 0.802513
      }
    },
    {
      "fixed_offset_from_reference_local_xyz_m": [
        0.0,
        0.0,
        0.0
      ],
      "fixed_offset_from_reference_xyz_m": [
        0.0,
        0.0,
        0.0
      ],
      "fixed_orientation_from_reference_rpy_rad": [
        -0.0,
        0.000371,
        -3.141592
      ],
      "has_separate_distribution": false,
      "mounted_on_graspable": "black_pawn_a_dynamic",
      "name": "black_pawn_a",
      "reference_graspable_object": "black_pawn_a_dynamic",
      "rotation_radius_from_graspable_m": 0.0,
      "spawn_rotation_note": "Mounted on graspable 'black_pawn_a_dynamic', which RLBench randomly positions and yaw-rotates (+/-pi) each episode; world range is the 'black_pawn_a_dynamic' observed envelope expanded by the mount radius.",
      "world_pose_after_reset": {
        "kind": "exact",
        "orientation_rpy_rad": [
          -4e-05,
          0.000369,
          -3.032824
        ],
        "position_xyz_m": [
          0.030132,
          0.045739,
          0.802513
        ],
        "quaternion_xyzw": [
          0.000185,
          1e-05,
          0.998522,
          -0.054358
        ],
        "source": "exact_after_one_rlbench_reset"
      },
      "world_position_range_due_to_task_root_sampling": {
        "kind": "mounted_on_graspable_envelope",
        "mounted_on_graspable": "black_pawn_a_dynamic",
        "n_resets_observed": 30,
        "rotation_radius_m": 0.0,
        "source": "observed_black_pawn_a_dynamic_range_expanded_by_mount_radius_for_full_yaw",
        "x_uniform_max_m": 0.442518,
        "x_uniform_min_m": 0.048295,
        "y_uniform_max_m": 0.366661,
        "y_uniform_min_m": -0.35406,
        "z_fixed_m": 0.802513
      }
    },
    {
      "fixed_offset_from_reference_local_xyz_m": [
        0.0,
        0.0,
        0.0
      ],
      "fixed_offset_from_reference_xyz_m": [
        0.0,
        0.0,
        0.0
      ],
      "fixed_orientation_from_reference_rpy_rad": [
        0.000345,
        2.6e-05,
        1.570796
      ],
      "has_separate_distribution": false,
      "mounted_on_graspable": "black_pawn_b_dynamic",
      "name": "black_pawn_b",
      "reference_graspable_object": "black_pawn_b_dynamic",
      "rotation_radius_from_graspable_m": 0.0,
      "spawn_rotation_note": "Mounted on graspable 'black_pawn_b_dynamic', which RLBench randomly positions and yaw-rotates (+/-pi) each episode; world range is the 'black_pawn_b_dynamic' observed envelope expanded by the mount radius.",
      "world_pose_after_reset": {
        "kind": "exact",
        "orientation_rpy_rad": [
          0.00034,
          6.4e-05,
          1.679565
        ],
        "position_xyz_m": [
          0.077733,
          0.050937,
          0.802513
        ],
        "quaternion_xyzw": [
          0.000137,
          -0.000105,
          0.744498,
          0.667625
        ],
        "source": "exact_after_one_rlbench_reset"
      },
      "world_position_range_due_to_task_root_sampling": {
        "kind": "mounted_on_graspable_envelope",
        "mounted_on_graspable": "black_pawn_b_dynamic",
        "n_resets_observed": 30,
        "rotation_radius_m": 0.0,
        "source": "observed_black_pawn_b_dynamic_range_expanded_by_mount_radius_for_full_yaw",
        "x_uniform_max_m": 0.414941,
        "x_uniform_min_m": 0.057369,
        "y_uniform_max_m": 0.327065,
        "y_uniform_min_m": -0.342909,
        "z_fixed_m": 0.802513
      }
    },
    {
      "fixed_offset_from_reference_local_xyz_m": [
        0.0,
        0.0,
        0.0
      ],
      "fixed_offset_from_reference_xyz_m": [
        0.0,
        0.0,
        0.0
      ],
      "fixed_orientation_from_reference_rpy_rad": [
        -0.0,
        0.000371,
        -3.141592
      ],
      "has_separate_distribution": false,
      "mounted_on_graspable": "black_pawn_c_dynamic",
      "name": "black_pawn_c",
      "reference_graspable_object": "black_pawn_c_dynamic",
      "rotation_radius_from_graspable_m": 0.0,
      "spawn_rotation_note": "Mounted on graspable 'black_pawn_c_dynamic', which RLBench randomly positions and yaw-rotates (+/-pi) each episode; world range is the 'black_pawn_c_dynamic' observed envelope expanded by the mount radius.",
      "world_pose_after_reset": {
        "kind": "exact",
        "orientation_rpy_rad": [
          -4e-05,
          0.000369,
          -3.032824
        ],
        "position_xyz_m": [
          0.124572,
          0.056052,
          0.802513
        ],
        "quaternion_xyzw": [
          0.000185,
          1e-05,
          0.998522,
          -0.054358
        ],
        "source": "exact_after_one_rlbench_reset"
      },
      "world_position_range_due_to_task_root_sampling": {
        "kind": "mounted_on_graspable_envelope",
        "mounted_on_graspable": "black_pawn_c_dynamic",
        "n_resets_observed": 30,
        "rotation_radius_m": 0.0,
        "source": "observed_black_pawn_c_dynamic_range_expanded_by_mount_radius_for_full_yaw",
        "x_uniform_max_m": 0.387807,
        "x_uniform_min_m": 0.066298,
        "y_uniform_max_m": 0.288103,
        "y_uniform_min_m": -0.335311,
        "z_fixed_m": 0.802513
      }
    },
    {
      "fixed_offset_from_reference_local_xyz_m": [
        0.0,
        0.0,
        0.0
      ],
      "fixed_offset_from_reference_xyz_m": [
        0.0,
        0.0,
        0.0
      ],
      "fixed_orientation_from_reference_rpy_rad": [
        0.000345,
        2.6e-05,
        1.570796
      ],
      "has_separate_distribution": false,
      "mounted_on_graspable": "black_pawn_d_dynamic",
      "name": "black_pawn_d",
      "reference_graspable_object": "black_pawn_d_dynamic",
      "rotation_radius_from_graspable_m": 0.0,
      "spawn_rotation_note": "Mounted on graspable 'black_pawn_d_dynamic', which RLBench randomly positions and yaw-rotates (+/-pi) each episode; world range is the 'black_pawn_d_dynamic' observed envelope expanded by the mount radius.",
      "world_pose_after_reset": {
        "kind": "exact",
        "orientation_rpy_rad": [
          0.00034,
          6.4e-05,
          1.679565
        ],
        "position_xyz_m": [
          0.172935,
          0.061333,
          0.802513
        ],
        "quaternion_xyzw": [
          0.000137,
          -0.000105,
          0.744498,
          0.667625
        ],
        "source": "exact_after_one_rlbench_reset"
      },
      "world_position_range_due_to_task_root_sampling": {
        "kind": "mounted_on_graspable_envelope",
        "mounted_on_graspable": "black_pawn_d_dynamic",
        "n_resets_observed": 30,
        "rotation_radius_m": 0.0,
        "source": "observed_black_pawn_d_dynamic_range_expanded_by_mount_radius_for_full_yaw",
        "x_uniform_max_m": 0.359789,
        "x_uniform_min_m": 0.075517,
        "y_uniform_max_m": 0.247874,
        "y_uniform_min_m": -0.327467,
        "z_fixed_m": 0.802513
      }
    },
    {
      "fixed_offset_from_reference_local_xyz_m": [
        0.0,
        0.0,
        0.0
      ],
      "fixed_offset_from_reference_xyz_m": [
        0.0,
        0.0,
        0.0
      ],
      "fixed_orientation_from_reference_rpy_rad": [
        0.000345,
        2.6e-05,
        1.570797
      ],
      "has_separate_distribution": false,
      "mounted_on_graspable": "black_pawn_e_dynamic",
      "name": "black_pawn_e",
      "reference_graspable_object": "black_pawn_e_dynamic",
      "rotation_radius_from_graspable_m": 0.0,
      "spawn_rotation_note": "Mounted on graspable 'black_pawn_e_dynamic', which RLBench randomly positions and yaw-rotates (+/-pi) each episode; world range is the 'black_pawn_e_dynamic' observed envelope expanded by the mount radius.",
      "world_pose_after_reset": {
        "kind": "exact",
        "orientation_rpy_rad": [
          0.00034,
          6.4e-05,
          1.679565
        ],
        "position_xyz_m": [
          0.231281,
          -0.029714,
          0.802513
        ],
        "quaternion_xyzw": [
          0.000137,
          -0.000105,
          0.744498,
          0.667625
        ],
        "source": "exact_after_one_rlbench_reset"
      },
      "world_position_range_due_to_task_root_sampling": {
        "kind": "mounted_on_graspable_envelope",
        "mounted_on_graspable": "black_pawn_e_dynamic",
        "n_resets_observed": 30,
        "rotation_radius_m": 0.0,
        "source": "observed_black_pawn_e_dynamic_range_expanded_by_mount_radius_for_full_yaw",
        "x_uniform_max_m": 0.382125,
        "x_uniform_min_m": 0.084591,
        "y_uniform_max_m": 0.242102,
        "y_uniform_min_m": -0.319746,
        "z_fixed_m": 0.802513
      }
    },
    {
      "fixed_offset_from_reference_local_xyz_m": [
        0.0,
        0.0,
        0.0
      ],
      "fixed_offset_from_reference_xyz_m": [
        0.0,
        0.0,
        0.0
      ],
      "fixed_orientation_from_reference_rpy_rad": [
        0.000345,
        2.6e-05,
        1.570797
      ],
      "has_separate_distribution": false,
      "mounted_on_graspable": "black_pawn_g_dynamic",
      "name": "black_pawn_g",
      "reference_graspable_object": "black_pawn_g_dynamic",
      "rotation_radius_from_graspable_m": 0.0,
      "spawn_rotation_note": "Mounted on graspable 'black_pawn_g_dynamic', which RLBench randomly positions and yaw-rotates (+/-pi) each episode; world range is the 'black_pawn_g_dynamic' observed envelope expanded by the mount radius.",
      "world_pose_after_reset": {
        "kind": "exact",
        "orientation_rpy_rad": [
          0.00034,
          6.4e-05,
          1.679565
        ],
        "position_xyz_m": [
          0.315737,
          0.076928,
          0.802513
        ],
        "quaternion_xyzw": [
          0.000137,
          -0.000105,
          0.744498,
          0.667625
        ],
        "source": "exact_after_one_rlbench_reset"
      },
      "world_position_range_due_to_task_root_sampling": {
        "kind": "mounted_on_graspable_envelope",
        "mounted_on_graspable": "black_pawn_g_dynamic",
        "n_resets_observed": 30,
        "rotation_radius_m": 0.0,
        "source": "observed_black_pawn_g_dynamic_range_expanded_by_mount_radius_for_full_yaw",
        "x_uniform_max_m": 0.432489,
        "x_uniform_min_m": 0.065451,
        "y_uniform_max_m": 0.274013,
        "y_uniform_min_m": -0.304304,
        "z_fixed_m": 0.802513
      }
    },
    {
      "fixed_offset_from_reference_local_xyz_m": [
        0.0,
        0.0,
        0.0
      ],
      "fixed_offset_from_reference_xyz_m": [
        0.0,
        0.0,
        0.0
      ],
      "fixed_orientation_from_reference_rpy_rad": [
        0.000345,
        2.6e-05,
        1.570796
      ],
      "has_separate_distribution": false,
      "mounted_on_graspable": "black_pawn_h_dynamic",
      "name": "black_pawn_h",
      "reference_graspable_object": "black_pawn_h_dynamic",
      "rotation_radius_from_graspable_m": 0.0,
      "spawn_rotation_note": "Mounted on graspable 'black_pawn_h_dynamic', which RLBench randomly positions and yaw-rotates (+/-pi) each episode; world range is the 'black_pawn_h_dynamic' observed envelope expanded by the mount radius.",
      "world_pose_after_reset": {
        "kind": "exact",
        "orientation_rpy_rad": [
          0.00034,
          6.4e-05,
          1.679565
        ],
        "position_xyz_m": [
          0.363338,
          0.082125,
          0.802513
        ],
        "quaternion_xyzw": [
          0.000137,
          -0.000105,
          0.744498,
          0.667625
        ],
        "source": "exact_after_one_rlbench_reset"
      },
      "world_position_range_due_to_task_root_sampling": {
        "kind": "mounted_on_graspable_envelope",
        "mounted_on_graspable": "black_pawn_h_dynamic",
        "n_resets_observed": 30,
        "rotation_radius_m": 0.0,
        "source": "observed_black_pawn_h_dynamic_range_expanded_by_mount_radius_for_full_yaw",
        "x_uniform_max_m": 0.469803,
        "x_uniform_min_m": 0.031128,
        "y_uniform_max_m": 0.310629,
        "y_uniform_min_m": -0.296582,
        "z_fixed_m": 0.802513
      }
    },
    {
      "fixed_offset_from_reference_local_xyz_m": [
        0.0,
        0.0,
        0.0
      ],
      "fixed_offset_from_reference_xyz_m": [
        0.0,
        0.0,
        0.0
      ],
      "fixed_orientation_from_reference_rpy_rad": [
        -0.0,
        0.000371,
        -3.141593
      ],
      "has_separate_distribution": false,
      "mounted_on_graspable": "black_queenside_rook_dynamic",
      "name": "black_queenside_rook",
      "reference_graspable_object": "black_queenside_rook_dynamic",
      "rotation_radius_from_graspable_m": 0.0,
      "spawn_rotation_note": "Mounted on graspable 'black_queenside_rook_dynamic', which RLBench randomly positions and yaw-rotates (+/-pi) each episode; world range is the 'black_queenside_rook_dynamic' observed envelope expanded by the mount radius.",
      "world_pose_after_reset": {
        "kind": "exact",
        "orientation_rpy_rad": [
          -4e-05,
          0.000369,
          -3.032824
        ],
        "position_xyz_m": [
          0.024934,
          0.093339,
          0.798546
        ],
        "quaternion_xyzw": [
          0.000185,
          1e-05,
          0.998522,
          -0.054357
        ],
        "source": "exact_after_one_rlbench_reset"
      },
      "world_position_range_due_to_task_root_sampling": {
        "kind": "mounted_on_graspable_envelope",
        "mounted_on_graspable": "black_queenside_rook_dynamic",
        "n_resets_observed": 30,
        "rotation_radius_m": 0.0,
        "source": "observed_black_queenside_rook_dynamic_range_expanded_by_mount_radius_for_full_yaw",
        "x_uniform_max_m": 0.481663,
        "x_uniform_min_m": 0.001279,
        "y_uniform_max_m": 0.393587,
        "y_uniform_min_m": -0.397887,
        "z_fixed_m": 0.798546
      }
    },
    {
      "fixed_offset_from_reference_local_xyz_m": [
        0.0,
        0.0,
        0.0
      ],
      "fixed_offset_from_reference_xyz_m": [
        0.0,
        0.0,
        0.0
      ],
      "fixed_orientation_from_reference_rpy_rad": [
        -0.0,
        0.000371,
        -3.141592
      ],
      "has_separate_distribution": false,
      "mounted_on_graspable": "black_kingside_rook_dynamic",
      "name": "black_kingside_rook",
      "reference_graspable_object": "black_kingside_rook_dynamic",
      "rotation_radius_from_graspable_m": 0.0,
      "spawn_rotation_note": "Mounted on graspable 'black_kingside_rook_dynamic', which RLBench randomly positions and yaw-rotates (+/-pi) each episode; world range is the 'black_kingside_rook_dynamic' observed envelope expanded by the mount radius.",
      "world_pose_after_reset": {
        "kind": "exact",
        "orientation_rpy_rad": [
          -4e-05,
          0.000369,
          -3.032824
        ],
        "position_xyz_m": [
          0.358139,
          0.129726,
          0.798546
        ],
        "quaternion_xyzw": [
          0.000185,
          1e-05,
          0.998522,
          -0.054358
        ],
        "source": "exact_after_one_rlbench_reset"
      },
      "world_position_range_due_to_task_root_sampling": {
        "kind": "mounted_on_graspable_envelope",
        "mounted_on_graspable": "black_kingside_rook_dynamic",
        "n_resets_observed": 30,
        "rotation_radius_m": 0.0,
        "source": "observed_black_kingside_rook_dynamic_range_expanded_by_mount_radius_for_full_yaw",
        "x_uniform_max_m": 0.499011,
        "x_uniform_min_m": 0.005686,
        "y_uniform_max_m": 0.341485,
        "y_uniform_min_m": -0.34384,
        "z_fixed_m": 0.798546
      }
    },
    {
      "fixed_offset_from_reference_local_xyz_m": [
        0.0,
        0.0,
        0.0
      ],
      "fixed_offset_from_reference_xyz_m": [
        0.0,
        0.0,
        0.0
      ],
      "fixed_orientation_from_reference_rpy_rad": [
        -0.0,
        0.000371,
        -3.141593
      ],
      "has_separate_distribution": false,
      "mounted_on_graspable": "black_queenside_bishop_dynamic",
      "name": "black_queenside_bishop",
      "reference_graspable_object": "black_queenside_bishop_dynamic",
      "rotation_radius_from_graspable_m": 0.0,
      "spawn_rotation_note": "Mounted on graspable 'black_queenside_bishop_dynamic', which RLBench randomly positions and yaw-rotates (+/-pi) each episode; world range is the 'black_queenside_bishop_dynamic' observed envelope expanded by the mount radius.",
      "world_pose_after_reset": {
        "kind": "exact",
        "orientation_rpy_rad": [
          -4e-05,
          0.000369,
          -3.032824
        ],
        "position_xyz_m": [
          0.120136,
          0.103736,
          0.810532
        ],
        "quaternion_xyzw": [
          0.000185,
          1e-05,
          0.998522,
          -0.054357
        ],
        "source": "exact_after_one_rlbench_reset"
      },
      "world_position_range_due_to_task_root_sampling": {
        "kind": "mounted_on_graspable_envelope",
        "mounted_on_graspable": "black_queenside_bishop_dynamic",
        "n_resets_observed": 30,
        "rotation_radius_m": 0.0,
        "source": "observed_black_queenside_bishop_dynamic_range_expanded_by_mount_radius_for_full_yaw",
        "x_uniform_max_m": 0.426511,
        "x_uniform_min_m": 0.019427,
        "y_uniform_max_m": 0.314396,
        "y_uniform_min_m": -0.382445,
        "z_fixed_m": 0.810532
      }
    },
    {
      "fixed_offset_from_reference_local_xyz_m": [
        0.0,
        0.0,
        0.0
      ],
      "fixed_offset_from_reference_xyz_m": [
        0.0,
        0.0,
        0.0
      ],
      "fixed_orientation_from_reference_rpy_rad": [
        -0.0,
        0.000371,
        -3.141592
      ],
      "has_separate_distribution": false,
      "mounted_on_graspable": "black_kingside_bishop_dynamic",
      "name": "black_kingside_bishop",
      "reference_graspable_object": "black_kingside_bishop_dynamic",
      "rotation_radius_from_graspable_m": 0.0,
      "spawn_rotation_note": "Mounted on graspable 'black_kingside_bishop_dynamic', which RLBench randomly positions and yaw-rotates (+/-pi) each episode; world range is the 'black_kingside_bishop_dynamic' observed envelope expanded by the mount radius.",
      "world_pose_after_reset": {
        "kind": "exact",
        "orientation_rpy_rad": [
          -4e-05,
          0.000369,
          -3.032824
        ],
        "position_xyz_m": [
          0.262938,
          0.11933,
          0.810532
        ],
        "quaternion_xyzw": [
          0.000185,
          1e-05,
          0.998522,
          -0.054358
        ],
        "source": "exact_after_one_rlbench_reset"
      },
      "world_position_range_due_to_task_root_sampling": {
        "kind": "mounted_on_graspable_envelope",
        "mounted_on_graspable": "black_kingside_bishop_dynamic",
        "n_resets_observed": 30,
        "rotation_radius_m": 0.0,
        "source": "observed_black_kingside_bishop_dynamic_range_expanded_by_mount_radius_for_full_yaw",
        "x_uniform_max_m": 0.446937,
        "x_uniform_min_m": 0.033612,
        "y_uniform_max_m": 0.287876,
        "y_uniform_min_m": -0.359282,
        "z_fixed_m": 0.810532
      }
    },
    {
      "fixed_offset_from_reference_local_xyz_m": [
        0.0,
        0.0,
        0.0
      ],
      "fixed_offset_from_reference_xyz_m": [
        0.0,
        0.0,
        0.0
      ],
      "fixed_orientation_from_reference_rpy_rad": [
        3.141383,
        -0.000275,
        1.570797
      ],
      "has_separate_distribution": false,
      "mounted_on_graspable": "black_king_dynamic",
      "name": "black_king",
      "reference_graspable_object": "black_king_dynamic",
      "rotation_radius_from_graspable_m": 0.0,
      "spawn_rotation_note": "Mounted on graspable 'black_king_dynamic', which RLBench randomly positions and yaw-rotates (+/-pi) each episode; world range is the 'black_king_dynamic' observed envelope expanded by the mount radius.",
      "world_pose_after_reset": {
        "kind": "exact",
        "orientation_rpy_rad": [
          3.141354,
          -0.000251,
          1.462028
        ],
        "position_xyz_m": [
          0.215338,
          0.114132,
          0.815519
        ],
        "quaternion_xyzw": [
          0.744498,
          -0.667625,
          -1.4e-05,
          0.000172
        ],
        "source": "exact_after_one_rlbench_reset"
      },
      "world_position_range_due_to_task_root_sampling": {
        "kind": "mounted_on_graspable_envelope",
        "mounted_on_graspable": "black_king_dynamic",
        "n_resets_observed": 30,
        "rotation_radius_m": 0.0,
        "source": "observed_black_king_dynamic_range_expanded_by_mount_radius_for_full_yaw",
        "x_uniform_max_m": 0.424343,
        "x_uniform_min_m": 0.037576,
        "y_uniform_max_m": 0.289941,
        "y_uniform_min_m": -0.367003,
        "z_fixed_m": 0.815519
      }
    },
    {
      "fixed_offset_from_reference_local_xyz_m": [
        0.0,
        0.0,
        0.0
      ],
      "fixed_offset_from_reference_xyz_m": [
        0.0,
        0.0,
        0.0
      ],
      "fixed_orientation_from_reference_rpy_rad": [
        -0.0,
        0.000371,
        -3.141592
      ],
      "has_separate_distribution": false,
      "mounted_on_graspable": "black_queen_dynamic",
      "name": "black_queen",
      "reference_graspable_object": "black_queen_dynamic",
      "rotation_radius_from_graspable_m": 0.0,
      "spawn_rotation_note": "Mounted on graspable 'black_queen_dynamic', which RLBench randomly positions and yaw-rotates (+/-pi) each episode; world range is the 'black_queen_dynamic' observed envelope expanded by the mount radius.",
      "world_pose_after_reset": {
        "kind": "exact",
        "orientation_rpy_rad": [
          -4e-05,
          0.000369,
          -3.032824
        ],
        "position_xyz_m": [
          0.167737,
          0.108934,
          0.813043
        ],
        "quaternion_xyzw": [
          0.000185,
          1e-05,
          0.998522,
          -0.054358
        ],
        "source": "exact_after_one_rlbench_reset"
      },
      "world_position_range_due_to_task_root_sampling": {
        "kind": "mounted_on_graspable_envelope",
        "mounted_on_graspable": "black_queen_dynamic",
        "n_resets_observed": 30,
        "rotation_radius_m": 0.0,
        "source": "observed_black_queen_dynamic_range_expanded_by_mount_radius_for_full_yaw",
        "x_uniform_max_m": 0.401749,
        "x_uniform_min_m": 0.061538,
        "y_uniform_max_m": 0.292006,
        "y_uniform_min_m": -0.374723,
        "z_fixed_m": 0.813043
      }
    }
  ],
  "task_base_rotation_rz_bounds_rad": [
    -3.14,
    3.14
  ],
  "task_boundary_root": "setup_chess",
  "task_boundary_root_world_pose_after_reset": {
    "kind": "exact",
    "orientation_rpy_rad": [
      -0.0,
      0.0,
      0.108769
    ],
    "position_xyz_m": [
      0.210061,
      -0.056125,
      0.752
    ],
    "quaternion_xyzw": [
      0.0,
      0.0,
      0.054358,
      0.998522
    ],
    "source": "exact_after_one_rlbench_reset"
  },
  "type": "Uniform for x/y; fixed z",
  "units": "meters"
}
