[
  {
    "cartesian_path_sample_count": 0,
    "cartesian_path_samples": null,
    "end_effector_location_after_waypoint": {
      "kind": "exact",
      "orientation_rpy_rad": [
        3.141579,
        0.24142,
        -3.141587
      ],
      "position_xyz_m": [
        0.278686,
        -0.008163,
        1.471517
      ],
      "quaternion_xyzw": [
        2e-06,
        0.992723,
        -7e-06,
        0.120417
      ],
      "source": "exact_after_reaching_waypoint_path"
    },
    "end_effector_relative_to_waypoint_after_waypoint": {
      "kind": "exact",
      "orientation_rpy_rad": [
        1.393383,
        -0.164609,
        -0.830416
      ],
      "position_xyz_m": [
        -0.005318,
        0.326039,
        0.093523
      ],
      "quaternion_xyzw": [
        0.610608,
        0.20027,
        -0.356605,
        0.678146
      ],
      "source": "exact_tip_pose_in_waypoint_frame_after_reaching_waypoint_path"
    },
    "fixed_offset_xyz_m": [
      2.2e-05,
      0.474987,
      0.058999
    ],
    "fixed_orientation_rpy_rad": [
      1.570796,
      -9e-06,
      8e-06
    ],
    "motion_type": "point",
    "name": "waypoint0",
    "parent": "oven",
    "relative_to": {
      "location_in_reference_frame": {
        "kind": "exact",
        "orientation_rpy_rad": [
          1.570796,
          -9e-06,
          8e-06
        ],
        "position_xyz_m": [
          2.2e-05,
          0.474987,
          0.058999
        ],
        "quaternion_xyzw": [
          0.707107,
          -6e-06,
          -0.0,
          0.707107
        ],
        "source": "exact_parent_local_offset"
      },
      "meaning": "Waypoint pose expressed in the coordinate frame of reference_name.",
      "reference_kind": "object",
      "reference_name": "oven"
    },
    "relative_to_nearest_object": {
      "location_in_reference_frame": {
        "kind": "exact",
        "orientation_rpy_rad": [
          1.570796,
          -9e-06,
          8e-06
        ],
        "position_xyz_m": [
          2.2e-05,
          0.474987,
          0.058999
        ],
        "quaternion_xyzw": [
          0.707107,
          -6e-06,
          -0.0,
          0.707107
        ],
        "source": "exact_waypoint_pose_in_nearest_object_frame"
      },
      "meaning": "Waypoint pose expressed in the nearest non-waypoint parent object's frame.",
      "reference_kind": "object",
      "reference_name": "oven"
    },
    "type": "DUMMY",
    "world_location": {
      "kind": "exact",
      "orientation_rpy_rad": [
        -1.570796,
        0.815746,
        -3.141585
      ],
      "position_xyz_m": [
        0.206933,
        -0.068381,
        1.145478
      ],
      "quaternion_xyzw": [
        0.280482,
        0.649099,
        0.649102,
        0.280477
      ],
      "source": "exact_after_one_rlbench_reset"
    },
    "world_orientation_rpy_rad": [
      -1.570796,
      0.815746,
      -3.141585
    ]
  },
  {
    "cartesian_path_sample_count": 0,
    "cartesian_path_samples": null,
    "end_effector_location_after_waypoint": {
      "kind": "exact",
      "orientation_rpy_rad": [
        3.14159,
        0.241559,
        3.141579
      ],
      "position_xyz_m": [
        0.278629,
        -0.008152,
        1.471601
      ],
      "quaternion_xyzw": [
        -7e-06,
        0.992715,
        -2e-06,
        0.120486
      ],
      "source": "exact_after_reaching_waypoint_path"
    },
    "end_effector_relative_to_waypoint_after_waypoint": {
      "kind": "exact",
      "orientation_rpy_rad": [
        1.39327,
        -0.164683,
        -0.830466
      ],
      "position_xyz_m": [
        -0.005266,
        0.326122,
        -0.156507
      ],
      "quaternion_xyzw": [
        0.610575,
        0.200238,
        -0.356654,
        0.67816
      ],
      "source": "exact_tip_pose_in_waypoint_frame_after_reaching_waypoint_path"
    },
    "fixed_offset_xyz_m": [
      1e-05,
      0.224991,
      0.059
    ],
    "fixed_orientation_rpy_rad": [
      1.570796,
      -2.6e-05,
      -0.0
    ],
    "motion_type": "point",
    "name": "waypoint1",
    "parent": "oven",
    "relative_to": {
      "location_in_reference_frame": {
        "kind": "exact",
        "orientation_rpy_rad": [
          1.570796,
          -2.6e-05,
          -0.0
        ],
        "position_xyz_m": [
          1e-05,
          0.224991,
          0.059
        ],
        "quaternion_xyzw": [
          0.707107,
          -9e-06,
          -9e-06,
          0.707107
        ],
        "source": "exact_parent_local_offset"
      },
      "meaning": "Waypoint pose expressed in the coordinate frame of reference_name.",
      "reference_kind": "object",
      "reference_name": "oven"
    },
    "relative_to_nearest_object": {
      "location_in_reference_frame": {
        "kind": "exact",
        "orientation_rpy_rad": [
          1.570796,
          -2.6e-05,
          -0.0
        ],
        "position_xyz_m": [
          1e-05,
          0.224991,
          0.059
        ],
        "quaternion_xyzw": [
          0.707107,
          -9e-06,
          -9e-06,
          0.707107
        ],
        "source": "exact_waypoint_pose_in_nearest_object_frame"
      },
      "meaning": "Waypoint pose expressed in the nearest non-waypoint parent object's frame.",
      "reference_kind": "object",
      "reference_name": "oven"
    },
    "type": "DUMMY",
    "world_location": {
      "kind": "exact",
      "orientation_rpy_rad": [
        -1.570796,
        0.815763,
        3.141592
      ],
      "position_xyz_m": [
        0.388995,
        0.10294,
        1.145478
      ],
      "quaternion_xyzw": [
        0.280485,
        0.649098,
        0.649098,
        0.280485
      ],
      "source": "exact_after_one_rlbench_reset"
    },
    "world_orientation_rpy_rad": [
      -1.570796,
      0.815763,
      3.141592
    ]
  },
  {
    "cartesian_path_sample_count": 25,
    "cartesian_path_samples": [
      {
        "orientation_rpy_rad": [
          -1.249905,
          0.789576,
          2.909639
        ],
        "position_xyz_m": [
          0.388995,
          0.10294,
          1.145478
        ],
        "relative_distance": 0.0
      },
      {
        "orientation_rpy_rad": [
          -1.212516,
          0.782966,
          2.883176
        ],
        "position_xyz_m": [
          0.38138,
          0.095773,
          1.143096
        ],
        "relative_distance": 0.041667
      },
      {
        "orientation_rpy_rad": [
          -1.17564,
          0.775666,
          2.857258
        ],
        "position_xyz_m": [
          0.373765,
          0.088607,
          1.140714
        ],
        "relative_distance": 0.083333
      },
      {
        "orientation_rpy_rad": [
          -1.139313,
          0.767696,
          2.831924
        ],
        "position_xyz_m": [
          0.36615,
          0.081441,
          1.138332
        ],
        "relative_distance": 0.125
      },
      {
        "orientation_rpy_rad": [
          -1.103562,
          0.759078,
          2.807206
        ],
        "position_xyz_m": [
          0.358535,
          0.074275,
          1.13595
        ],
        "relative_distance": 0.166667
      },
      {
        "orientation_rpy_rad": [
          -1.068387,
          0.749824,
          2.783118
        ],
        "position_xyz_m": [
          0.351057,
          0.067238,
          1.133062
        ],
        "relative_distance": 0.208333
      },
      {
        "orientation_rpy_rad": [
          -1.033725,
          0.739933,
          2.759645
        ],
        "position_xyz_m": [
          0.344151,
          0.060738,
          1.128056
        ],
        "relative_distance": 0.25
      },
      {
        "orientation_rpy_rad": [
          -0.999703,
          0.729456,
          2.736861
        ],
        "position_xyz_m": [
          0.337244,
          0.054238,
          1.123049
        ],
        "relative_distance": 0.291667
      },
      {
        "orientation_rpy_rad": [
          -0.966327,
          0.718415,
          2.714779
        ],
        "position_xyz_m": [
          0.330338,
          0.047738,
          1.118042
        ],
        "relative_distance": 0.333333
      },
      {
        "orientation_rpy_rad": [
          -0.933605,
          0.706833,
          2.693408
        ],
        "position_xyz_m": [
          0.323432,
          0.041238,
          1.113035
        ],
        "relative_distance": 0.375
      },
      {
        "orientation_rpy_rad": [
          -0.901537,
          0.694734,
          2.672755
        ],
        "position_xyz_m": [
          0.316526,
          0.034738,
          1.108028
        ],
        "relative_distance": 0.416667
      },
      {
        "orientation_rpy_rad": [
          -0.870122,
          0.68214,
          2.65282
        ],
        "position_xyz_m": [
          0.30962,
          0.028239,
          1.103021
        ],
        "relative_distance": 0.458333
      },
      {
        "orientation_rpy_rad": [
          -0.839355,
          0.669073,
          2.633603
        ],
        "position_xyz_m": [
          0.302713,
          0.021739,
          1.098014
        ],
        "relative_distance": 0.5
      },
      {
        "orientation_rpy_rad": [
          -0.809227,
          0.655556,
          2.6151
        ],
        "position_xyz_m": [
          0.295807,
          0.015239,
          1.093007
        ],
        "relative_distance": 0.541667
      },
      {
        "orientation_rpy_rad": [
          -0.779729,
          0.64161,
          2.597305
        ],
        "position_xyz_m": [
          0.288901,
          0.008739,
          1.088
        ],
        "relative_distance": 0.583333
      },
      {
        "orientation_rpy_rad": [
          -0.739297,
          0.621318,
          2.573438
        ],
        "position_xyz_m": [
          0.28272,
          0.002921,
          1.081589
        ],
        "relative_distance": 0.625
      },
      {
        "orientation_rpy_rad": [
          -0.693064,
          0.596391,
          2.54698
        ],
        "position_xyz_m": [
          0.276992,
          -0.002469,
          1.074298
        ],
        "relative_distance": 0.666667
      },
      {
        "orientation_rpy_rad": [
          -0.648399,
          0.570503,
          2.522358
        ],
        "position_xyz_m": [
          0.271265,
          -0.007859,
          1.067007
        ],
        "relative_distance": 0.708333
      },
      {
        "orientation_rpy_rad": [
          -0.605218,
          0.543739,
          2.499511
        ],
        "position_xyz_m": [
          0.265538,
          -0.013249,
          1.059716
        ],
        "relative_distance": 0.75
      },
      {
        "orientation_rpy_rad": [
          -0.563432,
          0.516175,
          2.478374
        ],
        "position_xyz_m": [
          0.259811,
          -0.018639,
          1.052425
        ],
        "relative_distance": 0.791667
      },
      {
        "orientation_rpy_rad": [
          -0.5424,
          0.501672,
          2.468124
        ],
        "position_xyz_m": [
          0.254898,
          -0.023263,
          1.044121
        ],
        "relative_distance": 0.833333
      },
      {
        "orientation_rpy_rad": [
          -0.526316,
          0.490296,
          2.460469
        ],
        "position_xyz_m": [
          0.25018,
          -0.027703,
          1.035575
        ],
        "relative_distance": 0.875
      },
      {
        "orientation_rpy_rad": [
          -0.510428,
          0.478814,
          2.453068
        ],
        "position_xyz_m": [
          0.245462,
          -0.032144,
          1.027029
        ],
        "relative_distance": 0.916667
      },
      {
        "orientation_rpy_rad": [
          -0.494729,
          0.46723,
          2.445916
        ],
        "position_xyz_m": [
          0.240743,
          -0.036584,
          1.018483
        ],
        "relative_distance": 0.958333
      },
      {
        "orientation_rpy_rad": [
          -0.479213,
          0.455548,
          2.439008
        ],
        "position_xyz_m": [
          0.236025,
          -0.041025,
          1.009937
        ],
        "relative_distance": 1.0
      }
    ],
    "end_effector_location_after_waypoint": {
      "kind": "exact",
      "orientation_rpy_rad": [
        3.141588,
        0.241529,
        -3.141585
      ],
      "position_xyz_m": [
        0.278671,
        -0.008156,
        1.471573
      ],
      "quaternion_xyzw": [
        4e-06,
        0.992717,
        -2e-06,
        0.120471
      ],
      "source": "exact_after_reaching_waypoint_path"
    },
    "end_effector_relative_to_waypoint_after_waypoint": {
      "kind": "exact",
      "orientation_rpy_rad": [
        2.974348,
        0.175078,
        -2.37184
      ],
      "position_xyz_m": [
        -0.044249,
        -0.005294,
        0.382704
      ],
      "quaternion_xyzw": [
        0.365932,
        0.922811,
        -0.044409,
        0.111987
      ],
      "source": "exact_tip_pose_in_waypoint_frame_after_reaching_waypoint_path"
    },
    "fixed_offset_xyz_m": [
      9e-06,
      0.337222,
      0.00239
    ],
    "fixed_orientation_rpy_rad": [
      0.0,
      0.0,
      -1.570822
    ],
    "motion_type": "predefined_cartesian_path",
    "name": "waypoint2",
    "parent": "oven",
    "relative_to": {
      "location_in_reference_frame": {
        "kind": "exact",
        "orientation_rpy_rad": [
          0.0,
          0.0,
          -1.570822
        ],
        "position_xyz_m": [
          9e-06,
          0.337222,
          0.00239
        ],
        "quaternion_xyzw": [
          0.0,
          0.0,
          -0.707116,
          0.707098
        ],
        "source": "exact_parent_local_offset"
      },
      "meaning": "Waypoint pose expressed in the coordinate frame of reference_name.",
      "reference_kind": "object",
      "reference_name": "oven"
    },
    "relative_to_nearest_object": {
      "location_in_reference_frame": {
        "kind": "exact",
        "orientation_rpy_rad": [
          0.0,
          0.0,
          -1.570822
        ],
        "position_xyz_m": [
          9e-06,
          0.337222,
          0.00239
        ],
        "quaternion_xyzw": [
          0.0,
          0.0,
          -0.707116,
          0.707098
        ],
        "source": "exact_waypoint_pose_in_nearest_object_frame"
      },
      "meaning": "Waypoint pose expressed in the nearest non-waypoint parent object's frame.",
      "reference_kind": "object",
      "reference_name": "oven"
    },
    "type": "PATH",
    "world_location": {
      "kind": "exact",
      "orientation_rpy_rad": [
        -0.0,
        0.0,
        0.755034
      ],
      "position_xyz_m": [
        0.307267,
        0.026024,
        1.088869
      ],
      "quaternion_xyzw": [
        0.0,
        0.0,
        0.368613,
        0.929583
      ],
      "source": "exact_after_one_rlbench_reset"
    },
    "world_orientation_rpy_rad": [
      -0.0,
      0.0,
      0.755034
    ]
  },
  {
    "cartesian_path_sample_count": 0,
    "cartesian_path_samples": null,
    "end_effector_location_after_waypoint": {
      "kind": "exact",
      "orientation_rpy_rad": [
        3.141576,
        0.241581,
        3.14159
      ],
      "position_xyz_m": [
        0.278626,
        -0.008145,
        1.471622
      ],
      "quaternion_xyzw": [
        -2e-06,
        0.992714,
        -9e-06,
        0.120497
      ],
      "source": "exact_after_reaching_waypoint_path"
    },
    "end_effector_relative_to_waypoint_after_waypoint": {
      "kind": "exact",
      "orientation_rpy_rad": [
        0.189306,
        0.512863,
        0.64664
      ],
      "position_xyz_m": [
        -0.236032,
        -0.005256,
        -0.305248
      ],
      "quaternion_xyzw": [
        0.166906,
        0.210366,
        0.328681,
        0.90546
      ],
      "source": "exact_tip_pose_in_waypoint_frame_after_reaching_waypoint_path"
    },
    "fixed_offset_xyz_m": [
      9e-06,
      0.366097,
      -0.000409
    ],
    "fixed_orientation_rpy_rad": [
      2.443458,
      5e-06,
      -1.570811
    ],
    "motion_type": "point",
    "name": "waypoint3",
    "parent": "oven",
    "relative_to": {
      "location_in_reference_frame": {
        "kind": "exact",
        "orientation_rpy_rad": [
          2.443458,
          5e-06,
          -1.570811
        ],
        "position_xyz_m": [
          9e-06,
          0.366097,
          -0.000409
        ],
        "quaternion_xyzw": [
          0.664457,
          0.664468,
          -0.241846,
          0.241846
        ],
        "source": "exact_parent_local_offset"
      },
      "meaning": "Waypoint pose expressed in the coordinate frame of reference_name.",
      "reference_kind": "object",
      "reference_name": "oven"
    },
    "relative_to_nearest_object": {
      "location_in_reference_frame": {
        "kind": "exact",
        "orientation_rpy_rad": [
          2.443458,
          5e-06,
          -1.570811
        ],
        "position_xyz_m": [
          9e-06,
          0.366097,
          -0.000409
        ],
        "quaternion_xyzw": [
          0.664457,
          0.664468,
          -0.241846,
          0.241846
        ],
        "source": "exact_waypoint_pose_in_nearest_object_frame"
      },
      "meaning": "Waypoint pose expressed in the nearest non-waypoint parent object's frame.",
      "reference_kind": "object",
      "reference_name": "oven"
    },
    "type": "DUMMY",
    "world_location": {
      "kind": "exact",
      "orientation_rpy_rad": [
        -2.619706,
        0.487135,
        2.253995
      ],
      "position_xyz_m": [
        0.286239,
        0.006235,
        1.08607
      ],
      "quaternion_xyzw": [
        -0.346402,
        0.873514,
        0.126078,
        0.317936
      ],
      "source": "exact_after_one_rlbench_reset"
    },
    "world_orientation_rpy_rad": [
      -2.619706,
      0.487135,
      2.253995
    ]
  },
  {
    "cartesian_path_sample_count": 0,
    "cartesian_path_samples": null,
    "end_effector_location_after_waypoint": {
      "kind": "exact",
      "orientation_rpy_rad": [
        3.141578,
        0.241631,
        3.141577
      ],
      "position_xyz_m": [
        0.278625,
        -0.008158,
        1.471641
      ],
      "quaternion_xyzw": [
        -8e-06,
        0.992711,
        -8e-06,
        0.120522
      ],
      "source": "exact_after_reaching_waypoint_path"
    },
    "end_effector_relative_to_waypoint_after_waypoint": {
      "kind": "exact",
      "orientation_rpy_rad": [
        0.189339,
        0.512823,
        0.646612
      ],
      "position_xyz_m": [
        -0.476421,
        -0.005271,
        -0.397279
      ],
      "quaternion_xyzw": [
        0.166912,
        0.210344,
        0.328672,
        0.905467
      ],
      "source": "exact_tip_pose_in_waypoint_frame_after_reaching_waypoint_path"
    },
    "fixed_offset_xyz_m": [
      1.2e-05,
      0.491096,
      -0.225409
    ],
    "fixed_orientation_rpy_rad": [
      2.443458,
      5e-06,
      -1.570811
    ],
    "motion_type": "point",
    "name": "waypoint4",
    "parent": "oven",
    "relative_to": {
      "location_in_reference_frame": {
        "kind": "exact",
        "orientation_rpy_rad": [
          2.443458,
          5e-06,
          -1.570811
        ],
        "position_xyz_m": [
          1.2e-05,
          0.491096,
          -0.225409
        ],
        "quaternion_xyzw": [
          0.664457,
          0.664468,
          -0.241846,
          0.241846
        ],
        "source": "exact_parent_local_offset"
      },
      "meaning": "Waypoint pose expressed in the coordinate frame of reference_name.",
      "reference_kind": "object",
      "reference_name": "oven"
    },
    "relative_to_nearest_object": {
      "location_in_reference_frame": {
        "kind": "exact",
        "orientation_rpy_rad": [
          2.443458,
          5e-06,
          -1.570811
        ],
        "position_xyz_m": [
          1.2e-05,
          0.491096,
          -0.225409
        ],
        "quaternion_xyzw": [
          0.664457,
          0.664468,
          -0.241846,
          0.241846
        ],
        "source": "exact_waypoint_pose_in_nearest_object_frame"
      },
      "meaning": "Waypoint pose expressed in the nearest non-waypoint parent object's frame.",
      "reference_kind": "object",
      "reference_name": "oven"
    },
    "type": "DUMMY",
    "world_location": {
      "kind": "exact",
      "orientation_rpy_rad": [
        -2.619705,
        0.487134,
        2.253995
      ],
      "position_xyz_m": [
        0.195208,
        -0.079429,
        0.86107
      ],
      "quaternion_xyzw": [
        -0.346402,
        0.873514,
        0.126078,
        0.317936
      ],
      "source": "exact_after_one_rlbench_reset"
    },
    "world_orientation_rpy_rad": [
      -2.619705,
      0.487134,
      2.253995
    ]
  }
]
