[
  {
    "cartesian_path_sample_count": 0,
    "cartesian_path_samples": null,
    "end_effector_location_after_waypoint": {
      "kind": "exact",
      "orientation_rpy_rad": [
        -3.141592,
        0.241418,
        3.141576
      ],
      "position_xyz_m": [
        0.278661,
        -0.008153,
        1.471527
      ],
      "quaternion_xyzw": [
        -8e-06,
        0.992724,
        -1e-06,
        0.120416
      ],
      "source": "exact_after_reaching_waypoint_path"
    },
    "end_effector_relative_to_waypoint_after_waypoint": {
      "kind": "exact",
      "orientation_rpy_rad": [
        -1.586874,
        -0.218246,
        -0.071814
      ],
      "position_xyz_m": [
        -0.041674,
        -0.567455,
        -0.041362
      ],
      "quaternion_xyzw": [
        0.70533,
        0.101773,
        -0.052545,
        -0.699565
      ],
      "source": "exact_tip_pose_in_waypoint_frame_after_reaching_waypoint_path"
    },
    "fixed_offset_xyz_m": [
      0.005839,
      0.0,
      -0.066745
    ],
    "fixed_orientation_rpy_rad": [
      -0.0,
      0.0,
      -0.0
    ],
    "motion_type": "point",
    "name": "waypoint0",
    "parent": "waypoint1",
    "relative_to": {
      "location_in_reference_frame": {
        "kind": "exact",
        "orientation_rpy_rad": [
          -0.0,
          0.0,
          -0.0
        ],
        "position_xyz_m": [
          0.005839,
          0.0,
          -0.066745
        ],
        "quaternion_xyzw": [
          0.0,
          0.0,
          0.0,
          1.0
        ],
        "source": "exact_parent_local_offset"
      },
      "meaning": "Waypoint pose expressed in the coordinate frame of reference_name.",
      "reference_kind": "waypoint",
      "reference_name": "waypoint1"
    },
    "relative_to_nearest_object": {
      "location_in_reference_frame": {
        "kind": "exact",
        "orientation_rpy_rad": [
          0.43665,
          -1.563891,
          2.03002
        ],
        "position_xyz_m": [
          0.192227,
          0.01703,
          -0.004088
        ],
        "quaternion_xyzw": [
          -0.503301,
          -0.493516,
          0.507911,
          0.495133
        ],
        "source": "exact_waypoint_pose_in_nearest_object_frame"
      },
      "meaning": "Waypoint pose expressed in the nearest non-waypoint parent object's frame.",
      "reference_kind": "object",
      "reference_name": "box_lid"
    },
    "type": "DUMMY",
    "world_location": {
      "kind": "exact",
      "orientation_rpy_rad": [
        1.573033,
        -0.070084,
        -3.118862
      ],
      "position_xyz_m": [
        0.247022,
        -0.046783,
        0.903571
      ],
      "quaternion_xyzw": [
        -0.032784,
        -0.707136,
        0.706118,
        0.016777
      ],
      "source": "exact_after_one_rlbench_reset"
    },
    "world_orientation_rpy_rad": [
      1.573033,
      -0.070084,
      -3.118862
    ]
  },
  {
    "cartesian_path_sample_count": 0,
    "cartesian_path_samples": null,
    "end_effector_location_after_waypoint": {
      "kind": "exact",
      "orientation_rpy_rad": [
        -3.141585,
        0.241436,
        3.141585
      ],
      "position_xyz_m": [
        0.278702,
        -0.008146,
        1.471522
      ],
      "quaternion_xyzw": [
        -3e-06,
        0.992723,
        3e-06,
        0.120425
      ],
      "source": "exact_after_reaching_waypoint_path"
    },
    "end_effector_relative_to_waypoint_after_waypoint": {
      "kind": "exact",
      "orientation_rpy_rad": [
        -1.585836,
        -0.21826,
        -0.071829
      ],
      "position_xyz_m": [
        -0.035868,
        -0.567099,
        -0.108715
      ],
      "quaternion_xyzw": [
        0.704965,
        0.101811,
        -0.052492,
        -0.699931
      ],
      "source": "exact_tip_pose_in_waypoint_frame_after_reaching_waypoint_path"
    },
    "fixed_offset_xyz_m": [
      0.125501,
      0.010997,
      -0.003539
    ],
    "fixed_orientation_rpy_rad": [
      0.43665,
      -1.563891,
      2.03002
    ],
    "motion_type": "point",
    "name": "waypoint1",
    "parent": "box_lid",
    "relative_to": {
      "location_in_reference_frame": {
        "kind": "exact",
        "orientation_rpy_rad": [
          0.43665,
          -1.563891,
          2.03002
        ],
        "position_xyz_m": [
          0.125501,
          0.010997,
          -0.003539
        ],
        "quaternion_xyzw": [
          -0.503301,
          -0.493516,
          0.507911,
          0.495133
        ],
        "source": "exact_parent_local_offset"
      },
      "meaning": "Waypoint pose expressed in the coordinate frame of reference_name.",
      "reference_kind": "object",
      "reference_name": "box_lid"
    },
    "relative_to_nearest_object": {
      "location_in_reference_frame": {
        "kind": "exact",
        "orientation_rpy_rad": [
          0.43665,
          -1.563891,
          2.03002
        ],
        "position_xyz_m": [
          0.125501,
          0.010997,
          -0.003539
        ],
        "quaternion_xyzw": [
          -0.503301,
          -0.493516,
          0.507911,
          0.495133
        ],
        "source": "exact_waypoint_pose_in_nearest_object_frame"
      },
      "meaning": "Waypoint pose expressed in the nearest non-waypoint parent object's frame.",
      "reference_kind": "object",
      "reference_name": "box_lid"
    },
    "type": "DUMMY",
    "world_location": {
      "kind": "exact",
      "orientation_rpy_rad": [
        1.573033,
        -0.070084,
        -3.118862
      ],
      "position_xyz_m": [
        0.248171,
        -0.113773,
        0.903554
      ],
      "quaternion_xyzw": [
        -0.032784,
        -0.707136,
        0.706118,
        0.016777
      ],
      "source": "exact_after_one_rlbench_reset"
    },
    "world_orientation_rpy_rad": [
      1.573033,
      -0.070084,
      -3.118862
    ]
  },
  {
    "cartesian_path_sample_count": 25,
    "cartesian_path_samples": [
      {
        "orientation_rpy_rad": [
          1.503035,
          -0.07289,
          3.136622
        ],
        "position_xyz_m": [
          0.248185,
          -0.113787,
          0.903566
        ],
        "relative_distance": 0.0
      },
      {
        "orientation_rpy_rad": [
          1.613858,
          -0.072919,
          -3.13848
        ],
        "position_xyz_m": [
          0.24804,
          -0.115771,
          0.922091
        ],
        "relative_distance": 0.041667
      },
      {
        "orientation_rpy_rad": [
          1.724673,
          -0.072056,
          -3.130443
        ],
        "position_xyz_m": [
          0.247896,
          -0.117755,
          0.940615
        ],
        "relative_distance": 0.083333
      },
      {
        "orientation_rpy_rad": [
          1.812149,
          -0.070889,
          -3.124193
        ],
        "position_xyz_m": [
          0.247604,
          -0.121745,
          0.958744
        ],
        "relative_distance": 0.125
      },
      {
        "orientation_rpy_rad": [
          1.886003,
          -0.069585,
          -3.119008
        ],
        "position_xyz_m": [
          0.247228,
          -0.126906,
          0.976642
        ],
        "relative_distance": 0.166667
      },
      {
        "orientation_rpy_rad": [
          1.959845,
          -0.067831,
          -3.113934
        ],
        "position_xyz_m": [
          0.246793,
          -0.132861,
          0.994232
        ],
        "relative_distance": 0.208333
      },
      {
        "orientation_rpy_rad": [
          2.033676,
          -0.06551,
          -3.109013
        ],
        "position_xyz_m": [
          0.246194,
          -0.141044,
          1.010959
        ],
        "relative_distance": 0.25
      },
      {
        "orientation_rpy_rad": [
          2.107483,
          -0.062832,
          -3.104278
        ],
        "position_xyz_m": [
          0.245596,
          -0.149226,
          1.027687
        ],
        "relative_distance": 0.291667
      },
      {
        "orientation_rpy_rad": [
          2.181254,
          -0.059894,
          -3.099753
        ],
        "position_xyz_m": [
          0.244815,
          -0.15989,
          1.042912
        ],
        "relative_distance": 0.333333
      },
      {
        "orientation_rpy_rad": [
          2.254997,
          -0.05664,
          -3.095456
        ],
        "position_xyz_m": [
          0.244014,
          -0.170845,
          1.05796
        ],
        "relative_distance": 0.375
      },
      {
        "orientation_rpy_rad": [
          2.328707,
          -0.053115,
          -3.091412
        ],
        "position_xyz_m": [
          0.243118,
          -0.183084,
          1.071885
        ],
        "relative_distance": 0.416667
      },
      {
        "orientation_rpy_rad": [
          2.402383,
          -0.049333,
          -3.087638
        ],
        "position_xyz_m": [
          0.242138,
          -0.196479,
          1.084797
        ],
        "relative_distance": 0.458333
      },
      {
        "orientation_rpy_rad": [
          2.476031,
          -0.045264,
          -3.084154
        ],
        "position_xyz_m": [
          0.241135,
          -0.210194,
          1.097311
        ],
        "relative_distance": 0.5
      },
      {
        "orientation_rpy_rad": [
          2.549656,
          -0.040845,
          -3.080983
        ],
        "position_xyz_m": [
          0.240006,
          -0.225621,
          1.107696
        ],
        "relative_distance": 0.541667
      },
      {
        "orientation_rpy_rad": [
          2.623254,
          -0.036204,
          -3.078147
        ],
        "position_xyz_m": [
          0.238877,
          -0.241048,
          1.11808
        ],
        "relative_distance": 0.583333
      },
      {
        "orientation_rpy_rad": [
          2.696838,
          -0.031438,
          -3.075659
        ],
        "position_xyz_m": [
          0.237657,
          -0.25771,
          1.12622
        ],
        "relative_distance": 0.625
      },
      {
        "orientation_rpy_rad": [
          2.770401,
          -0.026521,
          -3.073526
        ],
        "position_xyz_m": [
          0.236414,
          -0.274702,
          1.13376
        ],
        "relative_distance": 0.666667
      },
      {
        "orientation_rpy_rad": [
          2.859406,
          -0.020369,
          -3.071438
        ],
        "position_xyz_m": [
          0.235138,
          -0.292134,
          1.140008
        ],
        "relative_distance": 0.708333
      },
      {
        "orientation_rpy_rad": [
          2.969677,
          -0.012512,
          -3.069623
        ],
        "position_xyz_m": [
          0.233818,
          -0.310173,
          1.144475
        ],
        "relative_distance": 0.75
      },
      {
        "orientation_rpy_rad": [
          3.07801,
          -0.004645,
          -3.068693
        ],
        "position_xyz_m": [
          0.232496,
          -0.328239,
          1.148775
        ],
        "relative_distance": 0.791667
      },
      {
        "orientation_rpy_rad": [
          -3.131681,
          0.000716,
          -3.068544
        ],
        "position_xyz_m": [
          0.23114,
          -0.346778,
          1.150028
        ],
        "relative_distance": 0.833333
      },
      {
        "orientation_rpy_rad": [
          -3.058187,
          0.006073,
          -3.06879
        ],
        "position_xyz_m": [
          0.229783,
          -0.365317,
          1.151281
        ],
        "relative_distance": 0.875
      },
      {
        "orientation_rpy_rad": [
          -2.990591,
          0.010981,
          -3.069366
        ],
        "position_xyz_m": [
          0.228424,
          -0.383885,
          1.151638
        ],
        "relative_distance": 0.916667
      },
      {
        "orientation_rpy_rad": [
          -2.92572,
          0.015647,
          -3.07023
        ],
        "position_xyz_m": [
          0.227064,
          -0.402466,
          1.15158
        ],
        "relative_distance": 0.958333
      },
      {
        "orientation_rpy_rad": [
          -2.860839,
          0.020248,
          -3.071394
        ],
        "position_xyz_m": [
          0.225704,
          -0.421048,
          1.151522
        ],
        "relative_distance": 1.0
      }
    ],
    "end_effector_location_after_waypoint": {
      "kind": "exact",
      "orientation_rpy_rad": [
        3.141585,
        0.241413,
        -3.141584
      ],
      "position_xyz_m": [
        0.278715,
        -0.008164,
        1.471527
      ],
      "quaternion_xyzw": [
        4e-06,
        0.992724,
        -3e-06,
        0.120414
      ],
      "source": "exact_after_reaching_waypoint_path"
    },
    "end_effector_relative_to_waypoint_after_waypoint": {
      "kind": "exact",
      "orientation_rpy_rad": [
        -2.900809,
        -0.015225,
        1.499309
      ],
      "position_xyz_m": [
        0.111012,
        0.036681,
        1.470085
      ],
      "quaternion_xyzw": [
        0.727228,
        -0.675765,
        -0.087364,
        -0.082753
      ],
      "source": "exact_tip_pose_in_waypoint_frame_after_reaching_waypoint_path"
    },
    "fixed_offset_xyz_m": [
      0.033617,
      0.901385,
      -0.220836
    ],
    "fixed_orientation_rpy_rad": [
      1.569766,
      -0.022562,
      1.567798
    ],
    "motion_type": "predefined_cartesian_path",
    "name": "waypoint2",
    "parent": "waypoint1",
    "relative_to": {
      "location_in_reference_frame": {
        "kind": "exact",
        "orientation_rpy_rad": [
          1.569766,
          -0.022562,
          1.567798
        ],
        "position_xyz_m": [
          0.033617,
          0.901385,
          -0.220836
        ],
        "quaternion_xyzw": [
          0.494824,
          -0.504612,
          0.493829,
          0.506604
        ],
        "source": "exact_parent_local_offset"
      },
      "meaning": "Waypoint pose expressed in the coordinate frame of reference_name.",
      "reference_kind": "waypoint",
      "reference_name": "waypoint1"
    },
    "relative_to_nearest_object": {
      "location_in_reference_frame": {
        "kind": "exact",
        "orientation_rpy_rad": [
          -8e-06,
          0.00523,
          3.141539
        ],
        "position_xyz_m": [
          0.340646,
          0.024905,
          -0.906817
        ],
        "quaternion_xyzw": [
          0.002615,
          4e-06,
          0.999997,
          2.7e-05
        ],
        "source": "exact_waypoint_pose_in_nearest_object_frame"
      },
      "meaning": "Waypoint pose expressed in the nearest non-waypoint parent object's frame.",
      "reference_kind": "object",
      "reference_name": "box_lid"
    },
    "type": "PATH",
    "world_location": {
      "kind": "exact",
      "orientation_rpy_rad": [
        0.003253,
        -0.00024,
        -1.643856
      ],
      "position_xyz_m": [
        0.250547,
        0.109456,
        0.002135
      ],
      "quaternion_xyzw": [
        -0.001195,
        -0.00111,
        0.732459,
        -0.680809
      ],
      "source": "exact_after_one_rlbench_reset"
    },
    "world_orientation_rpy_rad": [
      0.003253,
      -0.00024,
      -1.643856
    ]
  },
  {
    "cartesian_path_sample_count": 0,
    "cartesian_path_samples": null,
    "end_effector_location_after_waypoint": {
      "kind": "exact",
      "orientation_rpy_rad": [
        -3.141585,
        0.241508,
        -3.141591
      ],
      "position_xyz_m": [
        0.27863,
        -0.008159,
        1.471586
      ],
      "quaternion_xyzw": [
        1e-06,
        0.992718,
        4e-06,
        0.120461
      ],
      "source": "exact_after_reaching_waypoint_path"
    },
    "end_effector_relative_to_waypoint_after_waypoint": {
      "kind": "exact",
      "orientation_rpy_rad": [
        0.237352,
        -0.237426,
        -0.098354
      ],
      "position_xyz_m": [
        -0.014456,
        0.473197,
        -0.205342
      ],
      "quaternion_xyzw": [
        -0.123203,
        0.11168,
        0.062473,
        -0.984096
      ],
      "source": "exact_tip_pose_in_waypoint_frame_after_reaching_waypoint_path"
    },
    "fixed_offset_xyz_m": [
      0.326358,
      -0.162152,
      0.011044
    ],
    "fixed_orientation_rpy_rad": [
      -1.604456,
      -1.309933,
      -1.582268
    ],
    "motion_type": "point",
    "name": "waypoint3",
    "parent": "box_base",
    "relative_to": {
      "location_in_reference_frame": {
        "kind": "exact",
        "orientation_rpy_rad": [
          -1.604456,
          -1.309933,
          -1.582268
        ],
        "position_xyz_m": [
          0.326358,
          -0.162152,
          0.011044
        ],
        "quaternion_xyzw": [
          -0.099722,
          -0.703133,
          -0.084167,
          0.698982
        ],
        "source": "exact_parent_local_offset"
      },
      "meaning": "Waypoint pose expressed in the coordinate frame of reference_name.",
      "reference_kind": "object",
      "reference_name": "box_base"
    },
    "relative_to_nearest_object": {
      "location_in_reference_frame": {
        "kind": "exact",
        "orientation_rpy_rad": [
          -1.604456,
          -1.309933,
          -1.582268
        ],
        "position_xyz_m": [
          0.326358,
          -0.162152,
          0.011044
        ],
        "quaternion_xyzw": [
          -0.099722,
          -0.703133,
          -0.084167,
          0.698982
        ],
        "source": "exact_waypoint_pose_in_nearest_object_frame"
      },
      "meaning": "Waypoint pose expressed in the nearest non-waypoint parent object's frame.",
      "reference_kind": "object",
      "reference_name": "box_base"
    },
    "type": "DUMMY",
    "world_location": {
      "kind": "exact",
      "orientation_rpy_rad": [
        -2.882146,
        0.027464,
        -3.049976
      ],
      "position_xyz_m": [
        0.226603,
        -0.409256,
        1.151112
      ],
      "quaternion_xyzw": [
        -0.047178,
        -0.990383,
        -0.129835,
        -0.007679
      ],
      "source": "exact_after_one_rlbench_reset"
    },
    "world_orientation_rpy_rad": [
      -2.882146,
      0.027464,
      -3.049976
    ]
  },
  {
    "cartesian_path_sample_count": 0,
    "cartesian_path_samples": null,
    "end_effector_location_after_waypoint": {
      "kind": "exact",
      "orientation_rpy_rad": [
        3.141581,
        0.241557,
        3.141593
      ],
      "position_xyz_m": [
        0.278668,
        -0.008162,
        1.471589
      ],
      "quaternion_xyzw": [
        -1e-06,
        0.992715,
        -6e-06,
        0.120485
      ],
      "source": "exact_after_reaching_waypoint_path"
    },
    "end_effector_relative_to_waypoint_after_waypoint": {
      "kind": "exact",
      "orientation_rpy_rad": [
        0.237366,
        -0.237476,
        -0.098357
      ],
      "position_xyz_m": [
        -0.013958,
        0.483496,
        -0.159873
      ],
      "quaternion_xyzw": [
        -0.123211,
        0.111704,
        0.062478,
        -0.984092
      ],
      "source": "exact_tip_pose_in_waypoint_frame_after_reaching_waypoint_path"
    },
    "fixed_offset_xyz_m": [
      -0.000537,
      -0.010298,
      -0.045472
    ],
    "fixed_orientation_rpy_rad": [
      -0.0,
      0.0,
      -0.0
    ],
    "motion_type": "point",
    "name": "waypoint4",
    "parent": "waypoint3",
    "relative_to": {
      "location_in_reference_frame": {
        "kind": "exact",
        "orientation_rpy_rad": [
          -0.0,
          0.0,
          -0.0
        ],
        "position_xyz_m": [
          -0.000537,
          -0.010298,
          -0.045472
        ],
        "quaternion_xyzw": [
          0.0,
          0.0,
          0.0,
          1.0
        ],
        "source": "exact_parent_local_offset"
      },
      "meaning": "Waypoint pose expressed in the coordinate frame of reference_name.",
      "reference_kind": "waypoint",
      "reference_name": "waypoint3"
    },
    "relative_to_nearest_object": {
      "location_in_reference_frame": {
        "kind": "exact",
        "orientation_rpy_rad": [
          -1.604456,
          -1.309933,
          -1.582268
        ],
        "position_xyz_m": [
          0.367637,
          -0.183833,
          0.011119
        ],
        "quaternion_xyzw": [
          -0.099722,
          -0.703133,
          -0.084167,
          0.698982
        ],
        "source": "exact_waypoint_pose_in_nearest_object_frame"
      },
      "meaning": "Waypoint pose expressed in the nearest non-waypoint parent object's frame.",
      "reference_kind": "object",
      "reference_name": "box_base"
    },
    "type": "DUMMY",
    "world_location": {
      "kind": "exact",
      "orientation_rpy_rad": [
        -2.882146,
        0.027464,
        -3.049976
      ],
      "position_xyz_m": [
        0.224946,
        -0.430874,
        1.192391
      ],
      "quaternion_xyzw": [
        -0.047178,
        -0.990383,
        -0.129835,
        -0.007679
      ],
      "source": "exact_after_one_rlbench_reset"
    },
    "world_orientation_rpy_rad": [
      -2.882146,
      0.027464,
      -3.049976
    ]
  },
  {
    "cartesian_path_sample_count": 0,
    "cartesian_path_samples": null,
    "end_effector_location_after_waypoint": {
      "kind": "exact",
      "orientation_rpy_rad": [
        3.141567,
        0.241603,
        -3.141584
      ],
      "position_xyz_m": [
        0.278615,
        -0.008162,
        1.471628
      ],
      "quaternion_xyzw": [
        3e-06,
        0.992712,
        -1.2e-05,
        0.120508
      ],
      "source": "exact_after_reaching_waypoint_path"
    },
    "end_effector_relative_to_waypoint_after_waypoint": {
      "kind": "exact",
      "orientation_rpy_rad": [
        0.018213,
        0.240596,
        3.065735
      ],
      "position_xyz_m": [
        0.07528,
        0.145402,
        -0.506322
      ],
      "quaternion_xyzw": [
        0.12026,
        -0.004484,
        0.992059,
        0.036552
      ],
      "source": "exact_tip_pose_in_waypoint_frame_after_reaching_waypoint_path"
    },
    "fixed_offset_xyz_m": [
      -1e-06,
      -2e-06,
      -0.160996
    ],
    "fixed_orientation_rpy_rad": [
      -0.0,
      0.0,
      -0.0
    ],
    "motion_type": "point",
    "name": "waypoint5",
    "parent": "waypoint6",
    "relative_to": {
      "location_in_reference_frame": {
        "kind": "exact",
        "orientation_rpy_rad": [
          -0.0,
          0.0,
          -0.0
        ],
        "position_xyz_m": [
          -1e-06,
          -2e-06,
          -0.160996
        ],
        "quaternion_xyzw": [
          -0.0,
          0.0,
          -0.0,
          1.0
        ],
        "source": "exact_parent_local_offset"
      },
      "meaning": "Waypoint pose expressed in the coordinate frame of reference_name.",
      "reference_kind": "waypoint",
      "reference_name": "waypoint6"
    },
    "relative_to_nearest_object": {
      "location_in_reference_frame": {
        "kind": "exact",
        "orientation_rpy_rad": [
          0.0,
          -1.56982,
          -0.223124
        ],
        "position_xyz_m": [
          0.177644,
          0.012953,
          -0.062035
        ],
        "quaternion_xyzw": [
          -0.079044,
          0.702838,
          0.078402,
          -0.702584
        ],
        "source": "exact_waypoint_pose_in_nearest_object_frame"
      },
      "meaning": "Waypoint pose expressed in the nearest non-waypoint parent object's frame.",
      "reference_kind": "object",
      "reference_name": "shoe2"
    },
    "type": "DUMMY",
    "world_location": {
      "kind": "exact",
      "orientation_rpy_rad": [
        3.141464,
        0.000332,
        0.073677
      ],
      "position_xyz_m": [
        0.21441,
        0.142322,
        0.965265
      ],
      "quaternion_xyzw": [
        -0.999322,
        0.03683,
        -0.000168,
        -5.8e-05
      ],
      "source": "exact_after_one_rlbench_reset"
    },
    "world_orientation_rpy_rad": [
      3.141464,
      0.000332,
      0.073677
    ]
  },
  {
    "cartesian_path_sample_count": 0,
    "cartesian_path_samples": null,
    "end_effector_location_after_waypoint": {
      "kind": "exact",
      "orientation_rpy_rad": [
        3.141587,
        0.241504,
        3.141574
      ],
      "position_xyz_m": [
        0.278647,
        -0.008155,
        1.471583
      ],
      "quaternion_xyzw": [
        -1e-05,
        0.992718,
        -4e-06,
        0.120459
      ],
      "source": "exact_after_reaching_waypoint_path"
    },
    "end_effector_relative_to_waypoint_after_waypoint": {
      "kind": "exact",
      "orientation_rpy_rad": [
        0.018225,
        0.240496,
        3.06571
      ],
      "position_xyz_m": [
        0.075312,
        0.145392,
        -0.667273
      ],
      "quaternion_xyzw": [
        0.12021,
        -0.00449,
        0.992065,
        0.036565
      ],
      "source": "exact_tip_pose_in_waypoint_frame_after_reaching_waypoint_path"
    },
    "fixed_offset_xyz_m": [
      0.016649,
      0.012816,
      -0.062107
    ],
    "fixed_orientation_rpy_rad": [
      0.0,
      -1.569883,
      -0.223124
    ],
    "motion_type": "point",
    "name": "waypoint6",
    "parent": "shoe2",
    "relative_to": {
      "location_in_reference_frame": {
        "kind": "exact",
        "orientation_rpy_rad": [
          0.0,
          -1.569883,
          -0.223124
        ],
        "position_xyz_m": [
          0.016649,
          0.012816,
          -0.062107
        ],
        "quaternion_xyzw": [
          -0.079044,
          0.702838,
          0.078402,
          -0.702584
        ],
        "source": "exact_parent_local_offset"
      },
      "meaning": "Waypoint pose expressed in the coordinate frame of reference_name.",
      "reference_kind": "object",
      "reference_name": "shoe2"
    },
    "relative_to_nearest_object": {
      "location_in_reference_frame": {
        "kind": "exact",
        "orientation_rpy_rad": [
          0.0,
          -1.569883,
          -0.223124
        ],
        "position_xyz_m": [
          0.016649,
          0.012816,
          -0.062107
        ],
        "quaternion_xyzw": [
          -0.079044,
          0.702838,
          0.078402,
          -0.702584
        ],
        "source": "exact_waypoint_pose_in_nearest_object_frame"
      },
      "meaning": "Waypoint pose expressed in the nearest non-waypoint parent object's frame.",
      "reference_kind": "object",
      "reference_name": "shoe2"
    },
    "type": "DUMMY",
    "world_location": {
      "kind": "exact",
      "orientation_rpy_rad": [
        3.141464,
        0.000332,
        0.073677
      ],
      "position_xyz_m": [
        0.214464,
        0.1423,
        0.80427
      ],
      "quaternion_xyzw": [
        -0.999322,
        0.03683,
        -0.000168,
        -5.8e-05
      ],
      "source": "exact_after_one_rlbench_reset"
    },
    "world_orientation_rpy_rad": [
      3.141464,
      0.000332,
      0.073677
    ]
  },
  {
    "cartesian_path_sample_count": 0,
    "cartesian_path_samples": null,
    "end_effector_location_after_waypoint": {
      "kind": "exact",
      "orientation_rpy_rad": [
        3.141585,
        0.241534,
        3.141589
      ],
      "position_xyz_m": [
        0.27862,
        -0.008156,
        1.471591
      ],
      "quaternion_xyzw": [
        -2e-06,
        0.992717,
        -4e-06,
        0.120474
      ],
      "source": "exact_after_reaching_waypoint_path"
    },
    "end_effector_relative_to_waypoint_after_waypoint": {
      "kind": "exact",
      "orientation_rpy_rad": [
        0.018226,
        0.240526,
        3.065724
      ],
      "position_xyz_m": [
        0.075287,
        0.145396,
        -0.506285
      ],
      "quaternion_xyzw": [
        0.120225,
        -0.004491,
        0.992063,
        0.036557
      ],
      "source": "exact_tip_pose_in_waypoint_frame_after_reaching_waypoint_path"
    },
    "fixed_offset_xyz_m": [
      -3e-06,
      -2e-06,
      -0.160996
    ],
    "fixed_orientation_rpy_rad": [
      -0.0,
      0.0,
      -0.0
    ],
    "motion_type": "point",
    "name": "waypoint7",
    "parent": "waypoint6",
    "relative_to": {
      "location_in_reference_frame": {
        "kind": "exact",
        "orientation_rpy_rad": [
          -0.0,
          0.0,
          -0.0
        ],
        "position_xyz_m": [
          -3e-06,
          -2e-06,
          -0.160996
        ],
        "quaternion_xyzw": [
          0.0,
          0.0,
          0.0,
          1.0
        ],
        "source": "exact_parent_local_offset"
      },
      "meaning": "Waypoint pose expressed in the coordinate frame of reference_name.",
      "reference_kind": "waypoint",
      "reference_name": "waypoint6"
    },
    "relative_to_nearest_object": {
      "location_in_reference_frame": {
        "kind": "exact",
        "orientation_rpy_rad": [
          0.0,
          -1.569883,
          -0.223124
        ],
        "position_xyz_m": [
          0.177645,
          0.012954,
          -0.062037
        ],
        "quaternion_xyzw": [
          -0.079044,
          0.702838,
          0.078402,
          -0.702584
        ],
        "source": "exact_waypoint_pose_in_nearest_object_frame"
      },
      "meaning": "Waypoint pose expressed in the nearest non-waypoint parent object's frame.",
      "reference_kind": "object",
      "reference_name": "shoe2"
    },
    "type": "DUMMY",
    "world_location": {
      "kind": "exact",
      "orientation_rpy_rad": [
        3.141464,
        0.000332,
        0.073677
      ],
      "position_xyz_m": [
        0.214407,
        0.142323,
        0.965266
      ],
      "quaternion_xyzw": [
        -0.999322,
        0.03683,
        -0.000168,
        -5.8e-05
      ],
      "source": "exact_after_one_rlbench_reset"
    },
    "world_orientation_rpy_rad": [
      3.141464,
      0.000332,
      0.073677
    ]
  },
  {
    "cartesian_path_sample_count": 0,
    "cartesian_path_samples": null,
    "end_effector_location_after_waypoint": {
      "kind": "exact",
      "orientation_rpy_rad": [
        3.141584,
        0.241402,
        -3.141589
      ],
      "position_xyz_m": [
        0.278674,
        -0.008164,
        1.471532
      ],
      "quaternion_xyzw": [
        1e-06,
        0.992724,
        -4e-06,
        0.120408
      ],
      "source": "exact_after_reaching_waypoint_path"
    },
    "end_effector_relative_to_waypoint_after_waypoint": {
      "kind": "exact",
      "orientation_rpy_rad": [
        0.017952,
        0.240746,
        3.066411
      ],
      "position_xyz_m": [
        0.074963,
        -0.294698,
        -0.508073
      ],
      "quaternion_xyzw": [
        0.120328,
        -0.004392,
        0.992063,
        0.036231
      ],
      "source": "exact_tip_pose_in_waypoint_frame_after_reaching_waypoint_path"
    },
    "fixed_offset_xyz_m": [
      0.138706,
      -0.053029,
      0.063333
    ],
    "fixed_orientation_rpy_rad": [
      0.0,
      -1.570796,
      3.141593
    ],
    "motion_type": "point",
    "name": "waypoint8",
    "parent": "box_base",
    "relative_to": {
      "location_in_reference_frame": {
        "kind": "exact",
        "orientation_rpy_rad": [
          0.0,
          -1.570796,
          3.141593
        ],
        "position_xyz_m": [
          0.138706,
          -0.053029,
          0.063333
        ],
        "quaternion_xyzw": [
          -0.707107,
          -1e-06,
          0.707106,
          -1e-06
        ],
        "source": "exact_parent_local_offset"
      },
      "meaning": "Waypoint pose expressed in the coordinate frame of reference_name.",
      "reference_kind": "object",
      "reference_name": "box_base"
    },
    "relative_to_nearest_object": {
      "location_in_reference_frame": {
        "kind": "exact",
        "orientation_rpy_rad": [
          0.0,
          -1.570796,
          3.141593
        ],
        "position_xyz_m": [
          0.138706,
          -0.053029,
          0.063333
        ],
        "quaternion_xyzw": [
          -0.707107,
          -1e-06,
          0.707106,
          -1e-06
        ],
        "source": "exact_waypoint_pose_in_nearest_object_frame"
      },
      "meaning": "Waypoint pose expressed in the nearest non-waypoint parent object's frame.",
      "reference_kind": "object",
      "reference_name": "box_base"
    },
    "type": "DUMMY",
    "world_location": {
      "kind": "exact",
      "orientation_rpy_rad": [
        3.14159,
        1e-06,
        0.073012
      ],
      "position_xyz_m": [
        0.182414,
        -0.296609,
        0.96346
      ],
      "quaternion_xyzw": [
        -0.999334,
        0.036498,
        -0.0,
        -1e-06
      ],
      "source": "exact_after_one_rlbench_reset"
    },
    "world_orientation_rpy_rad": [
      3.14159,
      1e-06,
      0.073012
    ]
  },
  {
    "cartesian_path_sample_count": 0,
    "cartesian_path_samples": null,
    "end_effector_location_after_waypoint": {
      "kind": "exact",
      "orientation_rpy_rad": [
        -3.141586,
        0.241476,
        3.141588
      ],
      "position_xyz_m": [
        0.278653,
        -0.008165,
        1.47156
      ],
      "quaternion_xyzw": [
        -2e-06,
        0.99272,
        3e-06,
        0.120445
      ],
      "source": "exact_after_reaching_waypoint_path"
    },
    "end_effector_relative_to_waypoint_after_waypoint": {
      "kind": "exact",
      "orientation_rpy_rad": [
        0.013838,
        0.240271,
        3.065037
      ],
      "position_xyz_m": [
        0.075739,
        0.271094,
        -0.507378
      ],
      "quaternion_xyzw": [
        -0.120019,
        0.002278,
        -0.992073,
        -0.037163
      ],
      "source": "exact_tip_pose_in_waypoint_frame_after_reaching_waypoint_path"
    },
    "fixed_offset_xyz_m": [
      -0.0,
      -3e-06,
      -0.160991
    ],
    "fixed_orientation_rpy_rad": [
      2e-06,
      -3e-06,
      6e-06
    ],
    "motion_type": "point",
    "name": "waypoint9",
    "parent": "waypoint10",
    "relative_to": {
      "location_in_reference_frame": {
        "kind": "exact",
        "orientation_rpy_rad": [
          2e-06,
          -3e-06,
          6e-06
        ],
        "position_xyz_m": [
          -0.0,
          -3e-06,
          -0.160991
        ],
        "quaternion_xyzw": [
          1e-06,
          -2e-06,
          3e-06,
          1.0
        ],
        "source": "exact_parent_local_offset"
      },
      "meaning": "Waypoint pose expressed in the coordinate frame of reference_name.",
      "reference_kind": "waypoint",
      "reference_name": "waypoint10"
    },
    "relative_to_nearest_object": {
      "location_in_reference_frame": {
        "kind": "exact",
        "orientation_rpy_rad": [
          -1.574908,
          -1.56547,
          1.449038
        ],
        "position_xyz_m": [
          0.177904,
          -0.019496,
          0.063251
        ],
        "quaternion_xyzw": [
          0.706,
          0.039694,
          -0.705762,
          -0.043458
        ],
        "source": "exact_waypoint_pose_in_nearest_object_frame"
      },
      "meaning": "Waypoint pose expressed in the nearest non-waypoint parent object's frame.",
      "reference_kind": "object",
      "reference_name": "shoe1"
    },
    "type": "DUMMY",
    "world_location": {
      "kind": "exact",
      "orientation_rpy_rad": [
        -3.137187,
        0.000855,
        0.074344
      ],
      "position_xyz_m": [
        0.223692,
        0.270039,
        0.965356
      ],
      "quaternion_xyzw": [
        0.999307,
        -0.037164,
        0.000345,
        -0.002217
      ],
      "source": "exact_after_one_rlbench_reset"
    },
    "world_orientation_rpy_rad": [
      -3.137187,
      0.000855,
      0.074344
    ]
  },
  {
    "cartesian_path_sample_count": 0,
    "cartesian_path_samples": null,
    "end_effector_location_after_waypoint": {
      "kind": "exact",
      "orientation_rpy_rad": [
        3.141592,
        0.241573,
        3.141584
      ],
      "position_xyz_m": [
        0.278627,
        -0.00815,
        1.471606
      ],
      "quaternion_xyzw": [
        -5e-06,
        0.992714,
        -1e-06,
        0.120493
      ],
      "source": "exact_after_reaching_waypoint_path"
    },
    "end_effector_relative_to_waypoint_after_waypoint": {
      "kind": "exact",
      "orientation_rpy_rad": [
        0.013839,
        0.240365,
        3.065037
      ],
      "position_xyz_m": [
        0.075713,
        0.271079,
        -0.668414
      ],
      "quaternion_xyzw": [
        -0.120066,
        0.002277,
        -0.992068,
        -0.037163
      ],
      "source": "exact_tip_pose_in_waypoint_frame_after_reaching_waypoint_path"
    },
    "fixed_offset_xyz_m": [
      0.016916,
      -0.018641,
      0.063246
    ],
    "fixed_orientation_rpy_rad": [
      -1.575625,
      -1.565492,
      1.448348
    ],
    "motion_type": "point",
    "name": "waypoint10",
    "parent": "shoe1",
    "relative_to": {
      "location_in_reference_frame": {
        "kind": "exact",
        "orientation_rpy_rad": [
          -1.575625,
          -1.565492,
          1.448348
        ],
        "position_xyz_m": [
          0.016916,
          -0.018641,
          0.063246
        ],
        "quaternion_xyzw": [
          0.706001,
          0.039696,
          -0.705761,
          -0.04346
        ],
        "source": "exact_parent_local_offset"
      },
      "meaning": "Waypoint pose expressed in the coordinate frame of reference_name.",
      "reference_kind": "object",
      "reference_name": "shoe1"
    },
    "relative_to_nearest_object": {
      "location_in_reference_frame": {
        "kind": "exact",
        "orientation_rpy_rad": [
          -1.575625,
          -1.565492,
          1.448348
        ],
        "position_xyz_m": [
          0.016916,
          -0.018641,
          0.063246
        ],
        "quaternion_xyzw": [
          0.706001,
          0.039696,
          -0.705761,
          -0.04346
        ],
        "source": "exact_waypoint_pose_in_nearest_object_frame"
      },
      "meaning": "Waypoint pose expressed in the nearest non-waypoint parent object's frame.",
      "reference_kind": "object",
      "reference_name": "shoe1"
    },
    "type": "DUMMY",
    "world_location": {
      "kind": "exact",
      "orientation_rpy_rad": [
        -3.137189,
        0.000858,
        0.074338
      ],
      "position_xyz_m": [
        0.22383,
        0.270744,
        0.804367
      ],
      "quaternion_xyzw": [
        0.999307,
        -0.037161,
        0.000347,
        -0.002216
      ],
      "source": "exact_after_one_rlbench_reset"
    },
    "world_orientation_rpy_rad": [
      -3.137189,
      0.000858,
      0.074338
    ]
  },
  {
    "cartesian_path_sample_count": 0,
    "cartesian_path_samples": null,
    "end_effector_location_after_waypoint": {
      "kind": "exact",
      "orientation_rpy_rad": [
        3.141587,
        0.241515,
        3.141579
      ],
      "position_xyz_m": [
        0.27866,
        -0.008155,
        1.471588
      ],
      "quaternion_xyzw": [
        -7e-06,
        0.992718,
        -4e-06,
        0.120464
      ],
      "source": "exact_after_reaching_waypoint_path"
    },
    "end_effector_relative_to_waypoint_after_waypoint": {
      "kind": "exact",
      "orientation_rpy_rad": [
        0.01383,
        0.240307,
        3.065033
      ],
      "position_xyz_m": [
        0.075746,
        0.271084,
        -0.507405
      ],
      "quaternion_xyzw": [
        -0.120037,
        0.002273,
        -0.992071,
        -0.037166
      ],
      "source": "exact_tip_pose_in_waypoint_frame_after_reaching_waypoint_path"
    },
    "fixed_offset_xyz_m": [
      -0.0,
      -3e-06,
      -0.160991
    ],
    "fixed_orientation_rpy_rad": [
      -0.0,
      0.0,
      -0.0
    ],
    "motion_type": "point",
    "name": "waypoint11",
    "parent": "waypoint10",
    "relative_to": {
      "location_in_reference_frame": {
        "kind": "exact",
        "orientation_rpy_rad": [
          -0.0,
          0.0,
          -0.0
        ],
        "position_xyz_m": [
          -0.0,
          -3e-06,
          -0.160991
        ],
        "quaternion_xyzw": [
          0.0,
          0.0,
          0.0,
          1.0
        ],
        "source": "exact_parent_local_offset"
      },
      "meaning": "Waypoint pose expressed in the coordinate frame of reference_name.",
      "reference_kind": "waypoint",
      "reference_name": "waypoint10"
    },
    "relative_to_nearest_object": {
      "location_in_reference_frame": {
        "kind": "exact",
        "orientation_rpy_rad": [
          -1.575625,
          -1.565492,
          1.448348
        ],
        "position_xyz_m": [
          0.177904,
          -0.019496,
          0.063251
        ],
        "quaternion_xyzw": [
          0.706001,
          0.039696,
          -0.705761,
          -0.04346
        ],
        "source": "exact_waypoint_pose_in_nearest_object_frame"
      },
      "meaning": "Waypoint pose expressed in the nearest non-waypoint parent object's frame.",
      "reference_kind": "object",
      "reference_name": "shoe1"
    },
    "type": "DUMMY",
    "world_location": {
      "kind": "exact",
      "orientation_rpy_rad": [
        -3.137189,
        0.000858,
        0.074338
      ],
      "position_xyz_m": [
        0.223692,
        0.270039,
        0.965356
      ],
      "quaternion_xyzw": [
        0.999307,
        -0.037161,
        0.000347,
        -0.002216
      ],
      "source": "exact_after_one_rlbench_reset"
    },
    "world_orientation_rpy_rad": [
      -3.137189,
      0.000858,
      0.074338
    ]
  },
  {
    "cartesian_path_sample_count": 0,
    "cartesian_path_samples": null,
    "end_effector_location_after_waypoint": {
      "kind": "exact",
      "orientation_rpy_rad": [
        3.141583,
        0.241516,
        -3.141591
      ],
      "position_xyz_m": [
        0.278659,
        -0.008159,
        1.471567
      ],
      "quaternion_xyzw": [
        0.0,
        0.992718,
        -5e-06,
        0.120465
      ],
      "source": "exact_after_reaching_waypoint_path"
    },
    "end_effector_relative_to_waypoint_after_waypoint": {
      "kind": "exact",
      "orientation_rpy_rad": [
        0.017963,
        0.240845,
        3.066425
      ],
      "position_xyz_m": [
        0.074952,
        -0.190697,
        -0.506111
      ],
      "quaternion_xyzw": [
        0.120377,
        -0.004396,
        0.992058,
        0.036223
      ],
      "source": "exact_tip_pose_in_waypoint_frame_after_reaching_waypoint_path"
    },
    "fixed_offset_xyz_m": [
      0.140703,
      0.05097,
      0.063326
    ],
    "fixed_orientation_rpy_rad": [
      0.0,
      -1.570796,
      3.141576
    ],
    "motion_type": "point",
    "name": "waypoint12",
    "parent": "box_base",
    "relative_to": {
      "location_in_reference_frame": {
        "kind": "exact",
        "orientation_rpy_rad": [
          0.0,
          -1.570796,
          3.141576
        ],
        "position_xyz_m": [
          0.140703,
          0.05097,
          0.063326
        ],
        "quaternion_xyzw": [
          -0.707112,
          -1e-05,
          0.707101,
          2e-06
        ],
        "source": "exact_parent_local_offset"
      },
      "meaning": "Waypoint pose expressed in the coordinate frame of reference_name.",
      "reference_kind": "object",
      "reference_name": "box_base"
    },
    "relative_to_nearest_object": {
      "location_in_reference_frame": {
        "kind": "exact",
        "orientation_rpy_rad": [
          0.0,
          -1.570796,
          3.141576
        ],
        "position_xyz_m": [
          0.140703,
          0.05097,
          0.063326
        ],
        "quaternion_xyzw": [
          -0.707112,
          -1e-05,
          0.707101,
          2e-06
        ],
        "source": "exact_waypoint_pose_in_nearest_object_frame"
      },
      "meaning": "Waypoint pose expressed in the nearest non-waypoint parent object's frame.",
      "reference_kind": "object",
      "reference_name": "box_base"
    },
    "type": "DUMMY",
    "world_location": {
      "kind": "exact",
      "orientation_rpy_rad": [
        3.141581,
        1.5e-05,
        0.072996
      ],
      "position_xyz_m": [
        0.190007,
        -0.192888,
        0.965457
      ],
      "quaternion_xyzw": [
        -0.999334,
        0.03649,
        -8e-06,
        -6e-06
      ],
      "source": "exact_after_one_rlbench_reset"
    },
    "world_orientation_rpy_rad": [
      3.141581,
      1.5e-05,
      0.072996
    ]
  }
]
