[
  {
    "cartesian_path_sample_count": 0,
    "cartesian_path_samples": null,
    "end_effector_location_after_waypoint": {
      "kind": "exact",
      "orientation_rpy_rad": [
        3.141579,
        0.241674,
        3.141589
      ],
      "position_xyz_m": [
        0.278592,
        -0.008161,
        1.471666
      ],
      "quaternion_xyzw": [
        -3e-06,
        0.992708,
        -7e-06,
        0.120543
      ],
      "source": "exact_after_reaching_waypoint_path"
    },
    "end_effector_relative_to_waypoint_after_waypoint": {
      "kind": "exact",
      "orientation_rpy_rad": [
        0.226837,
        0.739083,
        -2.036308
      ],
      "position_xyz_m": [
        -0.28111,
        0.232276,
        -0.332762
      ],
      "quaternion_xyzw": [
        0.250047,
        -0.278208,
        0.767125,
        -0.521149
      ],
      "source": "exact_tip_pose_in_waypoint_frame_after_reaching_waypoint_path"
    },
    "fixed_offset_xyz_m": [
      -4e-06,
      -6e-06,
      -0.063992
    ],
    "fixed_orientation_rpy_rad": [
      0.0,
      0.0,
      -0.0
    ],
    "motion_type": "point",
    "name": "waypoint0",
    "parent": "waypoint1",
    "relative_to": {
      "location_in_reference_frame": {
        "kind": "exact",
        "orientation_rpy_rad": [
          0.0,
          0.0,
          -0.0
        ],
        "position_xyz_m": [
          -4e-06,
          -6e-06,
          -0.063992
        ],
        "quaternion_xyzw": [
          0.0,
          0.0,
          0.0,
          1.0
        ],
        "source": "exact_parent_local_offset"
      },
      "meaning": "Waypoint pose expressed in the coordinate frame of reference_name.",
      "reference_kind": "waypoint",
      "reference_name": "waypoint1"
    },
    "relative_to_nearest_object": {
      "location_in_reference_frame": {
        "kind": "exact",
        "orientation_rpy_rad": [
          -1.57079,
          0.0,
          1.380555
        ],
        "position_xyz_m": [
          0.001575,
          -0.083239,
          -0.011146
        ],
        "quaternion_xyzw": [
          -0.545227,
          0.45025,
          0.450252,
          0.54523
        ],
        "source": "exact_waypoint_pose_in_nearest_object_frame"
      },
      "meaning": "Waypoint pose expressed in the nearest non-waypoint parent object's frame.",
      "reference_kind": "object",
      "reference_name": "mug0"
    },
    "type": "DUMMY",
    "world_location": {
      "kind": "exact",
      "orientation_rpy_rad": [
        2.383012,
        0.076026,
        -1.062175
      ],
      "position_xyz_m": [
        0.239674,
        0.018743,
        0.980561
      ],
      "quaternion_xyzw": [
        -0.793269,
        -0.482268,
        0.156951,
        -0.33691
      ],
      "source": "exact_after_one_rlbench_reset"
    },
    "world_orientation_rpy_rad": [
      2.383012,
      0.076026,
      -1.062175
    ]
  },
  {
    "cartesian_path_sample_count": 0,
    "cartesian_path_samples": null,
    "end_effector_location_after_waypoint": {
      "kind": "exact",
      "orientation_rpy_rad": [
        3.14159,
        0.241448,
        -3.14159
      ],
      "position_xyz_m": [
        0.278686,
        -0.008168,
        1.471542
      ],
      "quaternion_xyzw": [
        1e-06,
        0.992722,
        -1e-06,
        0.120431
      ],
      "source": "exact_after_reaching_waypoint_path"
    },
    "end_effector_relative_to_waypoint_after_waypoint": {
      "kind": "exact",
      "orientation_rpy_rad": [
        0.231704,
        0.733737,
        -2.025039
      ],
      "position_xyz_m": [
        -0.279792,
        0.235678,
        -0.395523
      ],
      "quaternion_xyzw": [
        0.245036,
        -0.280254,
        0.764457,
        -0.526328
      ],
      "source": "exact_tip_pose_in_waypoint_frame_after_reaching_waypoint_path"
    },
    "fixed_offset_xyz_m": [
      0.00157,
      -0.019247,
      -0.01115
    ],
    "fixed_orientation_rpy_rad": [
      -1.57079,
      0.0,
      1.380555
    ],
    "motion_type": "point",
    "name": "waypoint1",
    "parent": "mug0",
    "relative_to": {
      "location_in_reference_frame": {
        "kind": "exact",
        "orientation_rpy_rad": [
          -1.57079,
          0.0,
          1.380555
        ],
        "position_xyz_m": [
          0.00157,
          -0.019247,
          -0.01115
        ],
        "quaternion_xyzw": [
          -0.545227,
          0.45025,
          0.450253,
          0.54523
        ],
        "source": "exact_parent_local_offset"
      },
      "meaning": "Waypoint pose expressed in the coordinate frame of reference_name.",
      "reference_kind": "object",
      "reference_name": "mug0"
    },
    "relative_to_nearest_object": {
      "location_in_reference_frame": {
        "kind": "exact",
        "orientation_rpy_rad": [
          -1.57079,
          0.0,
          1.380555
        ],
        "position_xyz_m": [
          0.00157,
          -0.019247,
          -0.01115
        ],
        "quaternion_xyzw": [
          -0.545227,
          0.45025,
          0.450253,
          0.54523
        ],
        "source": "exact_waypoint_pose_in_nearest_object_frame"
      },
      "meaning": "Waypoint pose expressed in the nearest non-waypoint parent object's frame.",
      "reference_kind": "object",
      "reference_name": "mug0"
    },
    "type": "DUMMY",
    "world_location": {
      "kind": "exact",
      "orientation_rpy_rad": [
        2.383012,
        0.076026,
        -1.062175
      ],
      "position_xyz_m": [
        0.244542,
        -0.025148,
        0.934249
      ],
      "quaternion_xyzw": [
        -0.793269,
        -0.482268,
        0.156951,
        -0.33691
      ],
      "source": "exact_after_one_rlbench_reset"
    },
    "world_orientation_rpy_rad": [
      2.383012,
      0.076026,
      -1.062175
    ]
  },
  {
    "cartesian_path_sample_count": 0,
    "cartesian_path_samples": null,
    "end_effector_location_after_waypoint": {
      "kind": "exact",
      "orientation_rpy_rad": [
        3.141585,
        0.241723,
        -3.141583
      ],
      "position_xyz_m": [
        0.278575,
        -0.008155,
        1.471684
      ],
      "quaternion_xyzw": [
        4e-06,
        0.992705,
        -3e-06,
        0.120568
      ],
      "source": "exact_after_reaching_waypoint_path"
    },
    "end_effector_relative_to_waypoint_after_waypoint": {
      "kind": "exact",
      "orientation_rpy_rad": [
        0.307482,
        0.807862,
        -2.044808
      ],
      "position_xyz_m": [
        -0.305763,
        0.250735,
        -0.354929
      ],
      "quaternion_xyzw": [
        -0.258039,
        0.322643,
        -0.744055,
        0.52507
      ],
      "source": "exact_tip_pose_in_waypoint_frame_after_reaching_waypoint_path"
    },
    "fixed_offset_xyz_m": [
      0.016048,
      0.037898,
      -0.015213
    ],
    "fixed_orientation_rpy_rad": [
      1.324184,
      0.849134,
      0.149757
    ],
    "motion_type": "point",
    "name": "waypoint2",
    "parent": "place_cups_holder_spoke0",
    "relative_to": {
      "location_in_reference_frame": {
        "kind": "exact",
        "orientation_rpy_rad": [
          1.324184,
          0.849134,
          0.149757
        ],
        "position_xyz_m": [
          0.016048,
          0.037898,
          -0.015213
        ],
        "quaternion_xyzw": [
          -0.582922,
          -0.282072,
          -0.306293,
          -0.697726
        ],
        "source": "exact_parent_local_offset"
      },
      "meaning": "Waypoint pose expressed in the coordinate frame of reference_name.",
      "reference_kind": "object",
      "reference_name": "place_cups_holder_spoke0"
    },
    "relative_to_nearest_object": {
      "location_in_reference_frame": {
        "kind": "exact",
        "orientation_rpy_rad": [
          1.324184,
          0.849134,
          0.149757
        ],
        "position_xyz_m": [
          0.016048,
          0.037898,
          -0.015213
        ],
        "quaternion_xyzw": [
          -0.582922,
          -0.282072,
          -0.306293,
          -0.697726
        ],
        "source": "exact_waypoint_pose_in_nearest_object_frame"
      },
      "meaning": "Waypoint pose expressed in the nearest non-waypoint parent object's frame.",
      "reference_kind": "object",
      "reference_name": "place_cups_holder_spoke0"
    },
    "type": "DUMMY",
    "world_location": {
      "kind": "exact",
      "orientation_rpy_rad": [
        2.284379,
        0.114045,
        -1.067374
      ],
      "position_xyz_m": [
        0.247314,
        -0.026469,
        0.94157
      ],
      "quaternion_xyzw": [
        0.76974,
        0.482336,
        -0.166451,
        0.383597
      ],
      "source": "exact_after_one_rlbench_reset"
    },
    "world_orientation_rpy_rad": [
      2.284379,
      0.114045,
      -1.067374
    ]
  },
  {
    "cartesian_path_sample_count": 0,
    "cartesian_path_samples": null,
    "end_effector_location_after_waypoint": {
      "kind": "exact",
      "orientation_rpy_rad": [
        3.14159,
        0.241443,
        3.141583
      ],
      "position_xyz_m": [
        0.278675,
        -0.008153,
        1.471543
      ],
      "quaternion_xyzw": [
        -5e-06,
        0.992722,
        -2e-06,
        0.120429
      ],
      "source": "exact_after_reaching_waypoint_path"
    },
    "end_effector_relative_to_waypoint_after_waypoint": {
      "kind": "exact",
      "orientation_rpy_rad": [
        0.307792,
        0.807667,
        -2.045069
      ],
      "position_xyz_m": [
        -0.286211,
        0.154827,
        -0.358505
      ],
      "quaternion_xyzw": [
        -0.257921,
        0.322684,
        -0.744113,
        0.525021
      ],
      "source": "exact_tip_pose_in_waypoint_frame_after_reaching_waypoint_path"
    },
    "fixed_offset_xyz_m": [
      -0.019388,
      0.095922,
      0.003652
    ],
    "fixed_orientation_rpy_rad": [
      4e-05,
      7.2e-05,
      9e-06
    ],
    "motion_type": "point",
    "name": "waypoint3",
    "parent": "waypoint2",
    "relative_to": {
      "location_in_reference_frame": {
        "kind": "exact",
        "orientation_rpy_rad": [
          4e-05,
          7.2e-05,
          9e-06
        ],
        "position_xyz_m": [
          -0.019388,
          0.095922,
          0.003652
        ],
        "quaternion_xyzw": [
          2e-05,
          3.6e-05,
          5e-06,
          1.0
        ],
        "source": "exact_parent_local_offset"
      },
      "meaning": "Waypoint pose expressed in the coordinate frame of reference_name.",
      "reference_kind": "waypoint",
      "reference_name": "waypoint2"
    },
    "relative_to_nearest_object": {
      "location_in_reference_frame": {
        "kind": "exact",
        "orientation_rpy_rad": [
          1.324228,
          0.849211,
          0.149734
        ],
        "position_xyz_m": [
          -0.00333,
          0.033631,
          0.080686
        ],
        "quaternion_xyzw": [
          -0.582926,
          -0.282101,
          -0.306312,
          -0.697703
        ],
        "source": "exact_waypoint_pose_in_nearest_object_frame"
      },
      "meaning": "Waypoint pose expressed in the nearest non-waypoint parent object's frame.",
      "reference_kind": "object",
      "reference_name": "place_cups_holder_spoke0"
    },
    "type": "DUMMY",
    "world_location": {
      "kind": "exact",
      "orientation_rpy_rad": [
        2.284461,
        0.114045,
        -1.067374
      ],
      "position_xyz_m": [
        0.321913,
        -0.064193,
        0.992581
      ],
      "quaternion_xyzw": [
        0.769756,
        0.482343,
        -0.166431,
        0.383566
      ],
      "source": "exact_after_one_rlbench_reset"
    },
    "world_orientation_rpy_rad": [
      2.284461,
      0.114045,
      -1.067374
    ]
  },
  {
    "cartesian_path_sample_count": 0,
    "cartesian_path_samples": null,
    "end_effector_location_after_waypoint": {
      "kind": "exact",
      "orientation_rpy_rad": [
        3.141581,
        0.24167,
        3.141591
      ],
      "position_xyz_m": [
        0.278555,
        -0.008173,
        1.471692
      ],
      "quaternion_xyzw": [
        -1e-06,
        0.992708,
        -6e-06,
        0.120541
      ],
      "source": "exact_after_reaching_waypoint_path"
    },
    "end_effector_relative_to_waypoint_after_waypoint": {
      "kind": "exact",
      "orientation_rpy_rad": [
        -0.239505,
        0.032675,
        -1.703898
      ],
      "position_xyz_m": [
        -0.37612,
        0.08165,
        -0.584461
      ],
      "quaternion_xyzw": [
        -0.090867,
        -0.079213,
        -0.748361,
        0.652245
      ],
      "source": "exact_tip_pose_in_waypoint_frame_after_reaching_waypoint_path"
    },
    "fixed_offset_xyz_m": [
      -4e-06,
      -6e-06,
      -0.063992
    ],
    "fixed_orientation_rpy_rad": [
      0.0,
      0.0,
      -0.0
    ],
    "motion_type": "point",
    "name": "waypoint4",
    "parent": "waypoint5",
    "relative_to": {
      "location_in_reference_frame": {
        "kind": "exact",
        "orientation_rpy_rad": [
          0.0,
          0.0,
          -0.0
        ],
        "position_xyz_m": [
          -4e-06,
          -6e-06,
          -0.063992
        ],
        "quaternion_xyzw": [
          0.0,
          0.0,
          -0.0,
          1.0
        ],
        "source": "exact_parent_local_offset"
      },
      "meaning": "Waypoint pose expressed in the coordinate frame of reference_name.",
      "reference_kind": "waypoint",
      "reference_name": "waypoint5"
    },
    "relative_to_nearest_object": {
      "location_in_reference_frame": {
        "kind": "exact",
        "orientation_rpy_rad": [
          3.141582,
          -1.4e-05,
          -3.004563
        ],
        "position_xyz_m": [
          6e-06,
          -6e-06,
          0.139235
        ],
        "quaternion_xyzw": [
          0.068461,
          0.997654,
          -6e-06,
          -7e-06
        ],
        "source": "exact_waypoint_pose_in_nearest_object_frame"
      },
      "meaning": "Waypoint pose expressed in the nearest non-waypoint parent object's frame.",
      "reference_kind": "object",
      "reference_name": "success_detector0"
    },
    "type": "DUMMY",
    "world_location": {
      "kind": "exact",
      "orientation_rpy_rad": [
        -3.141579,
        -1.1e-05,
        -1.433767
      ],
      "position_xyz_m": [
        0.249043,
        0.375583,
        0.887237
      ],
      "quaternion_xyzw": [
        0.753857,
        0.657038,
        0.0,
        -9e-06
      ],
      "source": "exact_after_one_rlbench_reset"
    },
    "world_orientation_rpy_rad": [
      -3.141579,
      -1.1e-05,
      -1.433767
    ]
  },
  {
    "cartesian_path_sample_count": 0,
    "cartesian_path_samples": null,
    "end_effector_location_after_waypoint": {
      "kind": "exact",
      "orientation_rpy_rad": [
        3.141558,
        0.241606,
        -3.141586
      ],
      "position_xyz_m": [
        0.278651,
        -0.008168,
        1.471618
      ],
      "quaternion_xyzw": [
        1e-06,
        0.992712,
        -1.7e-05,
        0.120509
      ],
      "source": "exact_after_reaching_waypoint_path"
    },
    "end_effector_relative_to_waypoint_after_waypoint": {
      "kind": "exact",
      "orientation_rpy_rad": [
        -0.239444,
        0.032645,
        -1.703898
      ],
      "position_xyz_m": [
        -0.376107,
        0.081738,
        -0.648378
      ],
      "quaternion_xyzw": [
        -0.090836,
        -0.0792,
        -0.748363,
        0.65225
      ],
      "source": "exact_tip_pose_in_waypoint_frame_after_reaching_waypoint_path"
    },
    "fixed_offset_xyz_m": [
      1e-06,
      0.0,
      0.075243
    ],
    "fixed_orientation_rpy_rad": [
      3.141582,
      -1.4e-05,
      -3.004563
    ],
    "motion_type": "point",
    "name": "waypoint5",
    "parent": "success_detector0",
    "relative_to": {
      "location_in_reference_frame": {
        "kind": "exact",
        "orientation_rpy_rad": [
          3.141582,
          -1.4e-05,
          -3.004563
        ],
        "position_xyz_m": [
          1e-06,
          0.0,
          0.075243
        ],
        "quaternion_xyzw": [
          0.068461,
          0.997654,
          -6e-06,
          -6e-06
        ],
        "source": "exact_parent_local_offset"
      },
      "meaning": "Waypoint pose expressed in the coordinate frame of reference_name.",
      "reference_kind": "object",
      "reference_name": "success_detector0"
    },
    "relative_to_nearest_object": {
      "location_in_reference_frame": {
        "kind": "exact",
        "orientation_rpy_rad": [
          3.141582,
          -1.4e-05,
          -3.004563
        ],
        "position_xyz_m": [
          1e-06,
          0.0,
          0.075243
        ],
        "quaternion_xyzw": [
          0.068461,
          0.997654,
          -6e-06,
          -6e-06
        ],
        "source": "exact_waypoint_pose_in_nearest_object_frame"
      },
      "meaning": "Waypoint pose expressed in the nearest non-waypoint parent object's frame.",
      "reference_kind": "object",
      "reference_name": "success_detector0"
    },
    "type": "DUMMY",
    "world_location": {
      "kind": "exact",
      "orientation_rpy_rad": [
        -3.141579,
        -1.1e-05,
        -1.433766
      ],
      "position_xyz_m": [
        0.249048,
        0.375588,
        0.823245
      ],
      "quaternion_xyzw": [
        0.753857,
        0.657038,
        0.0,
        -9e-06
      ],
      "source": "exact_after_one_rlbench_reset"
    },
    "world_orientation_rpy_rad": [
      -3.141579,
      -1.1e-05,
      -1.433766
    ]
  }
]
