[
  {
    "analytical_task_root_yaw_range": {
      "kind": "range",
      "source": "rlbench_uniform_task_root_sampling_with_yaw_bounds",
      "x_uniform_max_m": 0.473415,
      "x_uniform_min_m": -0.083318,
      "y_uniform_max_m": 0.321248,
      "y_uniform_min_m": -0.428147,
      "z_fixed_m": 0.951388
    },
    "handle": 81,
    "hierarchy_path": "take_toilet_roll_off_stand/toilet_roll",
    "is_graspable": true,
    "name": "toilet_roll",
    "observed_spawn_yaw_range_rad": [
      -1.634863,
      -1.571146
    ],
    "observed_world_position_range_over_resets": {
      "mean_xyz_m": [
        0.186447,
        -0.076383,
        0.951384
      ],
      "n_resets_observed": 30,
      "x_max_m": 0.405946,
      "x_min_m": 0.011311,
      "y_max_m": 0.344916,
      "y_min_m": -0.376291,
      "z_max_m": 0.951511,
      "z_min_m": 0.951278
    },
    "parent": "take_toilet_roll_off_stand",
    "parent_local_location": {
      "kind": "exact",
      "orientation_rpy_rad": [
        -1.572534,
        -5.3e-05,
        -1.630162
      ],
      "position_xyz_m": [
        0.024613,
        0.0004,
        0.199388
      ],
      "quaternion_xyzw": [
        0.485348,
        0.515079,
        0.514159,
        -0.484533
      ],
      "source": "exact_parent_local_offset"
    },
    "placement_range": {
      "kind": "observed_over_rlbench_resets",
      "n_resets_observed": 30,
      "source": "observed_graspable_world_range_includes_spawn_translation_and_rotation",
      "x_uniform_max_m": 0.405946,
      "x_uniform_min_m": 0.011311,
      "y_uniform_max_m": 0.344916,
      "y_uniform_min_m": -0.376291,
      "z_fixed_m": 0.951384,
      "z_observed_max_m": 0.951511,
      "z_observed_min_m": 0.951278
    },
    "task_root_local_location": {
      "kind": "exact",
      "orientation_rpy_rad": [
        -1.572534,
        -5.3e-05,
        -1.630162
      ],
      "position_xyz_m": [
        0.024613,
        0.0004,
        0.199388
      ],
      "quaternion_xyzw": [
        0.485348,
        0.515079,
        0.514159,
        -0.484533
      ],
      "source": "exact_task_root_local_offset"
    },
    "type": "SHAPE",
    "world_location": {
      "kind": "exact",
      "orientation_rpy_rad": [
        -1.573012,
        0.669095,
        -1.628788
      ],
      "position_xyz_m": [
        0.100539,
        -0.259073,
        0.951388
      ],
      "quaternion_xyzw": [
        0.627571,
        0.327145,
        0.644753,
        -0.288832
      ],
      "source": "exact_after_one_rlbench_reset"
    },
    "world_position_range": {
      "kind": "observed_over_rlbench_resets",
      "n_resets_observed": 30,
      "source": "observed_graspable_world_range_includes_spawn_translation_and_rotation",
      "x_uniform_max_m": 0.405946,
      "x_uniform_min_m": 0.011311,
      "y_uniform_max_m": 0.344916,
      "y_uniform_min_m": -0.376291,
      "z_fixed_m": 0.951384,
      "z_observed_max_m": 0.951511,
      "z_observed_min_m": 0.951278
    }
  },
  {
    "fixed_relation_to_nearest_graspable": {
      "has_separate_position_range": false,
      "reference_local_location": {
        "kind": "exact",
        "orientation_rpy_rad": [
          1.542339,
          -1.511376,
          -1.893713
        ],
        "position_xyz_m": [
          -0.07141,
          0.047782,
          -0.002096
        ],
        "quaternion_xyzw": [
          -0.695477,
          -0.124368,
          0.702819,
          0.083004
        ],
        "source": "exact_reference_local_relation"
      },
      "reference_object": "toilet_roll",
      "world_offset_xyz_m": [
        0.039362,
        -0.033951,
        -0.068446
      ]
    },
    "handle": 83,
    "hierarchy_path": "take_toilet_roll_off_stand/stand_base",
    "name": "stand_base",
    "observed_world_position_range_over_resets": {
      "mean_xyz_m": [
        0.216722,
        -0.078163,
        0.882942
      ],
      "n_resets_observed": 30,
      "x_max_m": 0.455715,
      "x_min_m": 0.059082,
      "y_max_m": 0.326928,
      "y_min_m": -0.413532,
      "z_max_m": 0.882942,
      "z_min_m": 0.882942
    },
    "parent": "take_toilet_roll_off_stand",
    "parent_local_location": {
      "kind": "exact",
      "orientation_rpy_rad": [
        3.141544,
        -3e-05,
        1.276233
      ],
      "position_xyz_m": [
        0.076547,
        -0.001813,
        0.130943
      ],
      "quaternion_xyzw": [
        0.803219,
        -0.595684,
        2e-06,
        2.8e-05
      ],
      "source": "exact_parent_local_offset"
    },
    "placement_range": null,
    "task_root_local_location": {
      "kind": "exact",
      "orientation_rpy_rad": [
        3.141544,
        -3e-05,
        1.276233
      ],
      "position_xyz_m": [
        0.076547,
        -0.001813,
        0.130943
      ],
      "quaternion_xyzw": [
        0.803219,
        -0.595684,
        2e-06,
        2.8e-05
      ],
      "source": "exact_task_root_local_offset"
    },
    "type": "SHAPE",
    "world_location": {
      "kind": "exact",
      "orientation_rpy_rad": [
        3.141574,
        -5.4e-05,
        1.945382
      ],
      "position_xyz_m": [
        0.139901,
        -0.293025,
        0.882942
      ],
      "quaternion_xyzw": [
        0.563078,
        -0.826404,
        -7e-06,
        2.8e-05
      ],
      "source": "exact_after_one_rlbench_reset"
    },
    "world_position_range": {
      "kind": "range",
      "source": "rlbench_uniform_task_root_sampling_with_yaw_bounds",
      "x_uniform_max_m": 0.525367,
      "x_uniform_min_m": -0.135274,
      "y_uniform_max_m": 0.356407,
      "y_uniform_min_m": -0.4801,
      "z_fixed_m": 0.882942
    }
  },
  {
    "analytical_task_root_yaw_range": {
      "kind": "range",
      "source": "rlbench_uniform_task_root_sampling_with_yaw_bounds",
      "x_uniform_max_m": 0.473419,
      "x_uniform_min_m": -0.083322,
      "y_uniform_max_m": 0.321248,
      "y_uniform_min_m": -0.428151,
      "z_fixed_m": 0.951388
    },
    "fixed_relation_to_nearest_graspable": {
      "has_separate_position_range": false,
      "reference_local_location": {
        "kind": "exact",
        "orientation_rpy_rad": [
          3.14157,
          -0.000113,
          -0.390346
        ],
        "position_xyz_m": [
          0.0,
          4e-06,
          -5e-06
        ],
        "quaternion_xyzw": [
          0.981014,
          0.193936,
          -5.7e-05,
          0.0
        ],
        "source": "exact_reference_local_relation"
      },
      "reference_object": "toilet_roll",
      "world_offset_xyz_m": [
        -0.0,
        -6e-06,
        0.0
      ]
    },
    "handle": 82,
    "hierarchy_path": "take_toilet_roll_off_stand/toilet_roll/toilet_roll_visual",
    "mounted_note": "Rigidly mounted on graspable 'toilet_roll'. RLBench re-places 'toilet_roll' each episode at a random position within its spawn region and a random yaw (RLBench default +/-pi). This object sits ~0.0 m from 'toilet_roll' rotation axis, so its absolute world position sweeps a wide ring; its pose relative to 'toilet_roll' is fixed.",
    "mounted_on_graspable": "toilet_roll",
    "name": "toilet_roll_visual",
    "observed_world_position_range_over_resets": {
      "mean_xyz_m": [
        0.186449,
        -0.076386,
        0.951384
      ],
      "n_resets_observed": 30,
      "x_max_m": 0.405951,
      "x_min_m": 0.011314,
      "y_max_m": 0.344919,
      "y_min_m": -0.376297,
      "z_max_m": 0.951511,
      "z_min_m": 0.951278
    },
    "parent": "toilet_roll",
    "parent_local_location": {
      "kind": "exact",
      "orientation_rpy_rad": [
        3.14157,
        -0.000113,
        -0.390346
      ],
      "position_xyz_m": [
        0.0,
        4e-06,
        -5e-06
      ],
      "quaternion_xyzw": [
        0.981014,
        0.193936,
        -5.7e-05,
        0.0
      ],
      "source": "exact_parent_local_offset"
    },
    "placement_range": null,
    "rotation_radius_from_graspable_m": 6e-06,
    "task_root_local_location": {
      "kind": "exact",
      "orientation_rpy_rad": [
        1.569172,
        3.8e-05,
        1.239816
      ],
      "position_xyz_m": [
        0.024617,
        0.000395,
        0.199388
      ],
      "quaternion_xyzw": [
        -0.575077,
        0.410456,
        -0.411145,
        -0.575996
      ],
      "source": "exact_task_root_local_offset"
    },
    "type": "SHAPE",
    "world_location": {
      "kind": "exact",
      "orientation_rpy_rad": [
        1.568725,
        -0.669111,
        1.238531
      ],
      "position_xyz_m": [
        0.100539,
        -0.259079,
        0.951388
      ],
      "quaternion_xyzw": [
        -0.408409,
        0.576533,
        -0.199209,
        -0.679064
      ],
      "source": "exact_after_one_rlbench_reset"
    },
    "world_position_range": {
      "kind": "mounted_on_graspable_envelope",
      "mounted_on_graspable": "toilet_roll",
      "n_resets_observed": 30,
      "rotation_radius_m": 6e-06,
      "source": "observed_toilet_roll_range_expanded_by_mount_radius_for_full_yaw",
      "x_uniform_max_m": 0.405952,
      "x_uniform_min_m": 0.011305,
      "y_uniform_max_m": 0.344922,
      "y_uniform_min_m": -0.376297,
      "z_fixed_m": 0.951384
    }
  },
  {
    "fixed_relation_to_nearest_graspable": {
      "has_separate_position_range": false,
      "reference_local_location": {
        "kind": "exact",
        "orientation_rpy_rad": [
          3.14135,
          -0.001792,
          -1.62966
        ],
        "position_xyz_m": [
          0.037628,
          0.004193,
          -0.002267
        ],
        "quaternion_xyzw": [
          0.685992,
          0.727609,
          -0.000703,
          -0.000569
        ],
        "source": "exact_reference_local_relation"
      },
      "reference_object": "toilet_roll",
      "world_offset_xyz_m": [
        0.000167,
        -0.002938,
        0.037814
      ]
    },
    "handle": 84,
    "hierarchy_path": "take_toilet_roll_off_stand/stand_base/toilet_roll_holder",
    "name": "toilet_roll_holder",
    "observed_world_position_range_over_resets": {
      "mean_xyz_m": [
        0.187698,
        -0.077632,
        0.989202
      ],
      "n_resets_observed": 30,
      "x_max_m": 0.40861,
      "x_min_m": 0.013487,
      "y_max_m": 0.34616,
      "y_min_m": -0.379319,
      "z_max_m": 0.989202,
      "z_min_m": 0.989202
    },
    "parent": "stand_base",
    "parent_local_location": {
      "kind": "exact",
      "orientation_rpy_rad": [
        -1.570405,
        1.27615,
        0.000158
      ],
      "position_xyz_m": [
        -0.014517,
        0.04783,
        -0.106258
      ],
      "quaternion_xyzw": [
        0.567835,
        -0.421316,
        0.421061,
        -0.568124
      ],
      "source": "exact_parent_local_offset"
    },
    "placement_range": null,
    "task_root_local_location": {
      "kind": "exact",
      "orientation_rpy_rad": [
        1.570862,
        -8.3e-05,
        0.000502
      ],
      "position_xyz_m": [
        0.026566,
        -0.001802,
        0.237202
      ],
      "quaternion_xyzw": [
        -0.70713,
        0.000207,
        -0.000148,
        -0.707084
      ],
      "source": "exact_task_root_local_offset"
    },
    "type": "SHAPE",
    "world_location": {
      "kind": "exact",
      "orientation_rpy_rad": [
        1.57088,
        -0.669232,
        0.000554
      ],
      "position_xyz_m": [
        0.100705,
        -0.262012,
        0.989202
      ],
      "quaternion_xyzw": [
        -0.667852,
        0.232394,
        0.232043,
        -0.667925
      ],
      "source": "exact_after_one_rlbench_reset"
    },
    "world_position_range": {
      "kind": "range",
      "source": "rlbench_uniform_task_root_sampling_with_yaw_bounds",
      "x_uniform_max_m": 0.475426,
      "x_uniform_min_m": -0.085333,
      "y_uniform_max_m": 0.321073,
      "y_uniform_min_m": -0.430158,
      "z_fixed_m": 0.989202
    }
  },
  {
    "fixed_relation_to_nearest_graspable": {
      "has_separate_position_range": false,
      "reference_local_location": {
        "kind": "exact",
        "orientation_rpy_rad": [
          -0.000227,
          0.001785,
          1.630342
        ],
        "position_xyz_m": [
          0.037638,
          0.00418,
          -0.002268
        ],
        "quaternion_xyzw": [
          -0.000572,
          -0.000695,
          -0.727843,
          -0.685744
        ],
        "source": "exact_reference_local_relation"
      },
      "reference_object": "toilet_roll",
      "world_offset_xyz_m": [
        0.000155,
        -0.00293,
        0.037824
      ]
    },
    "handle": 85,
    "hierarchy_path": "take_toilet_roll_off_stand/stand_base/toilet_roll_holder/holder_visual",
    "name": "holder_visual",
    "observed_world_position_range_over_resets": {
      "mean_xyz_m": [
        0.187689,
        -0.077632,
        0.989212
      ],
      "n_resets_observed": 30,
      "x_max_m": 0.408597,
      "x_min_m": 0.013473,
      "y_max_m": 0.346167,
      "y_min_m": -0.37931,
      "z_max_m": 0.989212,
      "z_min_m": 0.989212
    },
    "parent": "toilet_roll_holder",
    "parent_local_location": {
      "kind": "exact",
      "orientation_rpy_rad": [
        3.141584,
        -1.6e-05,
        0.000682
      ],
      "position_xyz_m": [
        -1.4e-05,
        1e-05,
        1e-06
      ],
      "quaternion_xyzw": [
        1.0,
        -0.000341,
        -8e-06,
        4e-06
      ],
      "source": "exact_parent_local_offset"
    },
    "placement_range": null,
    "task_root_local_location": {
      "kind": "exact",
      "orientation_rpy_rad": [
        -1.570739,
        6.7e-05,
        0.00018
      ],
      "position_xyz_m": [
        0.026552,
        -0.001803,
        0.237212
      ],
      "quaternion_xyzw": [
        -0.707087,
        8.7e-05,
        4e-05,
        0.707127
      ],
      "source": "exact_task_root_local_offset"
    },
    "type": "SHAPE",
    "world_location": {
      "kind": "exact",
      "orientation_rpy_rad": [
        -1.570724,
        0.669217,
        0.000135
      ],
      "position_xyz_m": [
        0.100694,
        -0.262004,
        0.989212
      ],
      "quaternion_xyzw": [
        -0.66785,
        0.232267,
        -0.23216,
        0.66793
      ],
      "source": "exact_after_one_rlbench_reset"
    },
    "world_position_range": {
      "kind": "range",
      "source": "rlbench_uniform_task_root_sampling_with_yaw_bounds",
      "x_uniform_max_m": 0.475412,
      "x_uniform_min_m": -0.085319,
      "y_uniform_max_m": 0.321062,
      "y_uniform_min_m": -0.430144,
      "z_fixed_m": 0.989212
    }
  }
]
