{
  "hanger_holder": {
    "type": "kinematic",
    "uv": "auto"
  },
  "clothes_rack": {
    "type": "kinematic",
    "uv": "auto"
  },
  "hanger_holder0": {
    "type": "kinematic",
    "uv": "auto"
  },
  "hanger_holder_visual": {
    "type": "visual"
  },
  "clothes_hanger": {
    "type": "rigid",
    "density": 60.0,
    "uv": "auto"
  },
  "clothes_rack_sub2": {
    "type": "kinematic",
    "density": 60.0,
    "uv": "auto"
  },
  "clothes_rack_sub3": {
    "type": "kinematic",
    "density": 60.0,
    "uv": "auto"
  },
  "clothes_hanger_visual": {
    "type": "visual"
  }
}
